Workbook

Sheet Données
A1: ID | B1: Titre | C1: Catégorie | D1: imm_immo | E1: imm_treso | F1: imm_emprunts | G1: imm_capitaux | H1: imm_servExt | I1: imm_charPers | J1: rec_servExt | K1: rec_treso | L1: rec_charInt | M1: rec_charPers | N1: rec_revExcep | O1: rec_prodFin | P1: clientType | Q1: nbClients | R1: capaciteBonus | S1: imm_stocks | T1: rec_stocks | U1: rec_amort | V1: rec_cmv
A2: Commercial Junior | B2: Commercial Junior | C2: Commercial | D2: 0 | E2: -1000 | F2: 0 | G2: 0 | H2: 0 | I2: 1000 | J2: 0 | K2: -1000 | L2: 0 | M2: 1000 | N2: 0 | O2: 0 | P2: 0 | Q2: 0 | R2: 0 | S2: 0 | T2: 0 | U2: 0 | V2: 0
A3: Commercial Senior | B3: Commercial Senior | C3: Commercial | D3: 0 | E3: -2000 | F3: 0 | G3: 0 | H3: 0 | I3: 2000 | J3: 0 | K3: -2000 | L3: 0 | M3: 2000 | N3: 0 | O3: 0 | P3: 0 | Q3: 0 | R3: 0 | S3: 0 | T3: 0 | U3: 0 | V3: 0
A4: Directrice Commerciale | B4: Directrice Commerciale | C4: Commercial | D4: 0 | E4: -3000 | F4: 0 | G4: 0 | H4: 0 | I4: 3000 | J4: 0 | K4: -3000 | L4: 0 | M4: 3000 | N4: 0 | O4: 0 | P4: 0 | Q4: 0 | R4: 0 | S4: 0 | T4: 0 | U4: 0 | V4: 0
A5: Camionnette | B5: Camionnette | C5: Transport | D5: 8000 | E5: -8000 | F5: 0 | G5: 0 | H5: 0 | I5: 0 | J5: 1000 | K5: -1000 | L5: 0 | M5: 0 | N5: 0 | O5: 0 | P5: 1 | Q5: 1 | R5: 6 | S5: 0 | T5: 0 | U5: 0 | V5: 0
A6: Berline | B6: Berline | C6: Transport | D6: 8000 | E6: -8000 | F6: 0 | G6: 0 | H6: 0 | I6: 0 | J6: 2000 | K6: -2000 | L6: 0 | M6: 0 | N6: 0 | O6: 0 | P6: 0 | Q6: 0 | R6: 0 | S6: 0 | T6: 0 | U6: 0 | V6: 0
A7: Site Internet | B7: Site Internet | C7: Digital | D7: 4000 | E7: -4000 | F7: 0 | G7: 0 | H7: 0 | I7: 0 | J7: 1000 | K7: -1000 | L7: 0 | M7: 0 | N7: 0 | O7: 0 | P7: 1 | Q7: 1 | R7: 0 | S7: 0 | T7: 0 | U7: 0 | V7: 0
A8: RSE | B8: RSE | C8: Compliance | D8: 2000 | E8: 0 | F8: 2000 | G8: 0 | H8: 0 | I8: 0 | J8: 1000 | K8: -1000 | L8: 0 | M8: 0 | N8: 0 | O8: 0 | P8: 1 | Q8: 1 | R8: 0 | S8: 0 | T8: 0 | U8: 0 | V8: 0
A9: R&D | B9: R&D | C9: Innovation | D9: 5000 | E9: -5000 | F9: 0 | G9: 0 | H9: 0 | I9: 0 | J9: 2000 | K9: 0 | L9: 0 | M9: 0 | N9: 1000 | O9: 0 | P9: 2 | Q9: 1 | R9: 0 | S9: 0 | T9: 0 | U9: 0 | V9: 0
A10: Expansion | B10: Expansion | C10: Growth | D10: 8000 | E10: -8000 | F10: 0 | G10: 0 | H10: 0 | I10: 0 | J10: 1000 | K10: -1000 | L10: 0 | M10: 0 | N10: 0 | O10: 0 | P10: 3 | Q10: 1 | R10: 10 | S10: 0 | T10: 0 | U10: 0 | V10: 0
A11: Certification ISO | B11: Certification ISO | C11: Compliance | D11: 5000 | E11: -5000 | F11: 0 | G11: 0 | H11: 0 | I11: 0 | J11: 1000 | K11: -1000 | L11: 0 | M11: 0 | N11: 0 | O11: 0 | P11: 3 | Q11: 1 | R11: 0 | S11: 0 | T11: 0 | U11: 0 | V11: 0
A12: Application Mobile | B12: Application Mobile | C12: Digital | D12: 4000 | E12: -4000 | F12: 0 | G12: 0 | H12: 0 | I12: 0 | J12: 1000 | K12: -1000 | L12: 0 | M12: 0 | N12: 0 | O12: 0 | P12: 1 | Q12: 2 | R12: 0 | S12: 0 | T12: 0 | U12: 0 | V12: 0
A13: Prêt Bancaire | B13: Prêt Bancaire | C13: Finance | D13: 0 | E13: 5000 | F13: 5000 | G13: 0 | H13: 0 | I13: 0 | J13: 0 | K13: -1000 | L13: 1000 | M13: 0 | N13: 0 | O13: 0 | P13: 0 | Q13: 0 | R13: 0 | S13: 0 | T13: 0 | U13: 0 | V13: 0
... A38: Sous-traitance | B38: Sous-traitance | C38: Tactique | D38: 0 | E38: 0 | F38: 0 | G38: 0 | H38: 0 | I38: 0 | J38: 2000 | K38: -4000 | L38: 0 | M38: 0 | N38: 0 | O38: 0 | P38: 0 | Q38: 0 | R38: 0 | S38: 0 | T38: 2000 | U38: 0 | V38: 0
A44: ID | B44: Titre | C44: ventes | D44: treso | E44: stocks | F44: achats | G44: chargesExcep | H44: impots | I44: revenusExcep | J44: prodFin | K44: creancesPlus2 | L44: annulable
B45: Client VIP | C45: 2000 | D45: 2000 | E45: -2000 | F45: 2000 | G45: 0 | H45: 0 | I45: 0 | J45: 0 | K45: 0 | L45: 0
B46: Contrôle Fiscal | C46: 0 | D46: -2000 | E46: 0 | F46: 0 | G46: 0 | H46: 2000 | I46: 0 | J46: 0 | K46: 0 | L46: 1
B47: Subvention Innovation | C47: 0 | D47: 3000 | E47: 0 | F47: 0 | G47: 0 | H47: 0 | I47: 3000 | J47: 0 | K47: 0 | L47: 0
B48: Placement Financier | C48: 0 | D48: 1000 | E48: 0 | F48: 0 | G48: 0 | H48: 0 | I48: 0 | J48: 1000 | K48: 0 | L48: 0
B49: Crise Sanitaire | C49: 0 | D49: -2000 | E49: 0 | F49: 0 | G49: 2000 | H49: 0 | I49: 0 | J49: 0 | K49: 0 | L49: 1
B50: Incendie | C50: 0 | D50: 2000 | E50: 0 | F50: 0 | G50: 0 | H50: 0 | I50: 2000 | J50: 0 | K50: 0 | L50: 0
B51: Grève | C51: 0 | D51: -2000 | E51: 0 | F51: 0 | G51: 2000 | H51: 0 | I51: 0 | J51: 0 | K51: 0 | L51: 1
B52: Bouche à Oreille | C52: 1000 | D52: 1000 | E52: 0 | F52: 0 | G52: 0 | H52: 0 | I52: 0 | J52: 0 | K52: 0 | L52: 0
B53: Perte de Données | C53: 0 | D53: -2000 | E53: 0 | F53: 0 | G53: 2000 | H53: 0 | I53: 0 | J53: 0 | K53: 0 | L53: 1
B54: Développement Durable | C54: 3000 | D54: 0 | E54: -3000 | F54: 3000 | G54: 0 | H54: 0 | I54: 0 | J54: 0 | K54: 3000 | L54: 0
B55: Prix PME | C55: 0 | D55: 2000 | E55: 0 | F55: 0 | G55: 0 | H55: 0 | I55: 2000 | J55: 0 | K55: 0 | L55: 0
B56: Rupture Fournisseur | C56: 0 | D56: -2000 | E56: 0 | F56: 0 | G56: 2000 | H56: 0 | I56: 0 | J56: 0 | K56: 0 | L56: 0
B57: Litige Commercial | C57: 0 | D57: -3000 | E57: 0 | F57: 0 | G57: 3000 | H57: 0 | I57: 0 | J57: 0 | K57: 0 | L57: 1
A64: Nom | B64: Icon | C64: Type | D64: Spécialité | E64: immo_init | F64: nb_immo_items | G64: stocks_init | H64: treso_init | I64: capitaux_init | J64: emprunts_init
A65: Manufacture Belvaux | B65: 🏭 | C65: Production | D65: +1 prodStockée +1 stocks | E65: 16000 | F65: 2 | G65: 4000 | H65: 8000 | I65: 20000 | J65: 8000
A66: Véloce Transports | B66: 🚚 | C66: Logistique | D66: Encaissement -1 délai | E66: 16000 | F66: 2 | G66: 4000 | H66: 8000 | I66: 20000 | J66: 8000
A67: Azura Commerce | B67: 🏪 | C67: Commerce | D67: +1 client Particulier/tour | E67: 16000 | F67: 2 | G67: 4000 | H67: 8000 | I67: 20000 | J67: 8000
A68: Synergia Lab | B68: 💡 | C68: Innovation | D68: +1 prodFinanciers +1 tréso | E68: 13000 | F68: 2 | G68: 4000 | H68: 8000 | I68: 17000 | J68: 8000

Sheet Partie
A1: JE DEVIENS PATRON — Simulateur de Partie
A2: Entreprise: | B2: Manufacture Belvaux | D2: Nb Trimestres: | E2: 6
A4: 🎮 TOUR | D4: ✏️ VOS CHOIX | J4: 📊 BILAN | R4: ⚖️ ÉQUILIBRE | V4: 💹 COMPTE DE RÉSULTAT (cumulé) | AD4: 🏆 SCORE | AE4: 📈 EFFETS CE TOUR
A5: Tour | B5: Année | C5: Trim | D5: 💰 Emprunt | E5: 📦 Achat Qté | F5: 💳 Mode Paie. | G5: 👤 Recrutement | H5: 🃏 Carte Déc. | I5: ⚡ Événement | J5: 🏗️ Immob | K5: 📦 Stocks | L5: 💵 Trésorerie | M5: ⏳ C+1 | N5: ⌛ C+2 | O5: 🧾 Dettes | P5: 🏦 Emprunts | Q5: 💼 Capitaux | R5: ∑ Actif | S5: ∑ Passif | T5: 📈 Résultat | U5: ✓ Équil. | V5: 📤 Ventes | W5: 📥 CMV | X5: 👥 Ch.Pers | Y5: 💳 Ch.Int | Z5: 📉 Amort | AA5: ➕ Rev.Exc | AB5: ➖ Ch.Exc | AC5: 🏁 Résult.CR | AD5: ⭐ Score | AE5: ΔTréso | AF5: ΔRésultat | AG5: Ventes/T | AH5: Charges/T
A6: 0 | B6: =QUOTIENT(A6-1,4)+1 -> 1 | C6: =MOD(A6-1,4)+1 -> 4 | D6: — | E6: — | F6: — | G6: — | H6: — | I6: — | J6: =IFERROR(VLOOKUP($B$2,Données!$A$60:$J$63,5,FALSE()),0) -> 0 | K6: =IFERROR(VLOOKUP($B$2,Données!$A$60:$J$63,7,FALSE()),0) -> 0 | L6: =IFERROR(VLOOKUP($B$2,Données!$A$60:$J$63,8,FALSE()),0) -> 0 | M6: 0 | N6: 0 | O6: 0 | P6: =IFERROR(VLOOKUP($B$2,Données!$A$60:$J$63,10,FALSE()),0) -> 0 | Q6: =IFERROR(VLOOKUP($B$2,Données!$A$60:$J$63,9,FALSE()),0) -> 0 | R6: =J6+K6+MAX(0,L6)+M6+N6 -> 0 | S6: =Q6+P6+O6+MAX(0,-L6)+T6 -> 0 | T6: =R6-Q6-P6-O6-MAX(0,-L6) -> 0 | U6: =IF(ABS(R6-S6)<0.01,"✓","⚠") -> ✓ | V6: 0 | W6: 0 | X6: 0 | Y6: 0 | Z6: 0 | AA6: 0 | AB6: 0 | AC6: =V6-W6-X6-Y6-Z6+AA6-AB6 -> 0 | AD6: =T6*3+J6*2+MAX(0,L6)+Q6-MAX(0,-L6) -> 0 | AE6: 0 | AF6: 0 | AG6: 0 | AH6: 0
A7: =IF(A6+1<=$E$2,1,"") -> 1 | B7: =IF(A7="","",QUOTIENT(A7-1,4)+1) -> 1 | C7: =IF(A7="","",MOD(A7-1,4)+1) -> 1 | J7: =IF(A7="","",MAX(0,J6+IFERROR(VLOOKUP(H7,Données!$B$2:$R$33,3,FALSE()),0)-(2+IF(IFERROR(VLOOKUP(H7,Données!$B$2:$R$33,3,FALSE()),0)>0,1,0)))) -> 0 | K7: =IF(A7="","",MAX(0,K6+E7+IF($B$2="Manufacture Belvaux",1,0)+IFERROR(VLOOKUP(I7,Données!$B$44:$L$57,4,FALSE()),0)-(COUNTIF($G$7:G7,"Commercial Junior")+COUNTIF($G$7:G7,"Commercial Senior")+COUNTIF($G$7:G7,"Directrice Commerciale"))*2-IF($B$2="Azura Commerce",1,0)+IFERROR(VLOOKUP(H7,Données!$B$2:$V$38,19,FALSE()),0)+SUMPRODUCT(IFERROR(VLOOKUP($H$7:H7,Données!$B$2:$V$38,20,FALSE()),0)))) -> 1 | L7: =IF(A7="","",L6+D7-IF(F7="Comptant",E7,0)+COUNTIF($G$7:G7,"Commercial Junior")*4+IF($B$2="Véloce Transports",COUNTIF($G$7:G7,"Commercial Senior")*6,0)+IF($B$2="Azura Commerce",2,0)+M6+IFERROR(VLOOKUP(H7,Données!$B$2:$R$33,4,FALSE()),0)+SUMPRODUCT(IFERROR(VLOOKUP($H$7:H7,Données!$B$2:$R$33,10,FALSE()),0))+IFERROR(VLOOKUP(I7,Données!$B$39:$L$52,3,FALSE()),0)-(COUNTIF($G$7:G7,"Commercial Junior")*1+COUNTIF($G$7:G7,"Commercial Senior")*2+COUNTIF($G$7:G7,"Directrice Commerciale")*3)-IF(MOD(A7-1,4)=0,MAX(1,ROUND(P6*0.05,0)),0)+IF($B$2="Synergia Lab",1,0)) -> -1 | M7: =IF(A7="","",N6+IF($B$2<>"Véloce Transports",COUNTIF($G$7:G7,"Commercial Senior")*6,0)) -> 0 | N7: =IF(A7="","",COUNTIF($G$7:G7,"Directrice Commerciale")*8+IFERROR(VLOOKUP(I7,Données!$B$39:$L$52,10,FALSE()),0)) -> 0 | O7: =IF(A7="","",O6+IF(F7="Crédit",E7,0)) -> 0 | P7: =IF(A7="","",P6+D7+IFERROR(VLOOKUP(H7,Données!$B$2:$R$33,5,FALSE()),0)) -> 0 | Q7: =IF(A7="","",Q6+IFERROR(VLOOKUP(H7,Données!$B$2:$R$33,6,FALSE()),0)) -> 0 | R7: =IF(A7="","",J7+K7+MAX(0,L7)+M7+N7) -> 1 | S7: =IF(A7="","",Q7+P7+O7+MAX(0,-L7)+T7) -> 1 | T7: =IF(A7="","",R7-Q7-P7-O7-MAX(0,-L7)) -> 0 | U7: =IF(A7="","",IF(ABS(R7-S7)<0.01,"✓","⚠")) -> ✓ | V7: =IF(A7="","",V6+COUNTIF($G$7:G7,"Commercial Junior")*4+COUNTIF($G$7:G7,"Commercial Senior")*6+COUNTIF($G$7:G7,"Directrice Commerciale")*8+IF($B$2="Azura Commerce",2,0)+IFERROR(VLOOKUP(I7,Données!$B$44:$L$57,2,FALSE()),0)) -> 0 | W7: =IF(A7="","",W6+(COUNTIF($G$7:G7,"Commercial Junior")+COUNTIF($G$7:G7,"Commercial Senior")+COUNTIF($G$7:G7,"Directrice Commerciale"))*2+IF($B$2="Azura Commerce",1,0)+IFERROR(VLOOKUP(I7,Données!$B$44:$L$57,5,FALSE()),0)+SUMPRODUCT(IFERROR(VLOOKUP($H$7:H7,Données!$B$2:$V$38,22,FALSE()),0))) -> 0 | X7: =IF(A7="","",X6+COUNTIF($G$7:G7,"Commercial Junior")*1+COUNTIF($G$7:G7,"Commercial Senior")*2+COUNTIF($G$7:G7,"Directrice Commerciale")*3+SUMPRODUCT(IFERROR(VLOOKUP($H$7:H7,Données!$B$2:$V$38,12,FALSE()),0))) -> 0 | Y7: =IF(A7="","",Y6+IF(MOD(A7-1,4)=0,MAX(1,ROUND(P6*0.05,0)),0)+SUMPRODUCT(IFERROR(VLOOKUP($H$7:H7,Données!$B$2:$V$38,11,FALSE()),0))) -> 1 | Z7: =IF(A7="","",MAX(0,Z6+MIN(J6+IFERROR(VLOOKUP(H7,Données!$B$2:$V$38,3,FALSE()),0),2+IF(IFERROR(VLOOKUP(H7,Données!$B$2:$V$38,3,FALSE()),0)>0,1,0))+SUMPRODUCT(IFERROR(VLOOKUP($H$7:H7,Données!$B$2:$V$38,21,FALSE()),0)))) -> 0 | AA7: =IF(A7="","",AA6+IFERROR(VLOOKUP(I7,Données!$B$39:$L$52,8,FALSE()),0)+SUMPRODUCT(IFERROR(VLOOKUP($H$7:H7,Données!$B$2:$R$33,13,FALSE()),0))) -> 0 | AB7: =IF(A7="","",AB6+IFERROR(VLOOKUP(I7,Données!$B$39:$L$52,6,FALSE()),0)+IFERROR(VLOOKUP(I7,Données!$B$39:$L$52,7,FALSE()),0)) -> 0 | AC7: =IF(A7="","",V7-W7-X7-Y7-Z7+AA7-AB7) -> -1 | AD7: =IF(A7="","",T7*3+J7*2+MAX(0,L7)+Q7-MAX(0,-L7)) -> -1 | AE7: =IF(A7="","",L7-L6) -> -1 | AF7: =IF(A7="","",T7-T6) -> 0 | AG7: =IF(A7="","",V7-V6) -> 0 | AH7: =IF(A7="","",W7+X7+Y7+Z7-W6-X6-Y6-Z6) -> 1
A8: =IF(A6+2<=$E$2,2,"") -> 2 | B8: =IF(A8="","",QUOTIENT(A8-1,4)+1) -> 1 | C8: =IF(A8="","",MOD(A8-1,4)+1) -> 2 | J8: =IF(A8="","",MAX(0,J7+IFERROR(VLOOKUP(H8,Données!$B$2:$R$33,3,FALSE()),0)-(2+IF(IFERROR(VLOOKUP(H8,Données!$B$2:$R$33,3,FALSE()),0)>0,1,0)))) -> 0 | K8: =IF(A8="","",MAX(0,K7+E8+IF($B$2="Manufacture Belvaux",1,0)+IFERROR(VLOOKUP(I8,Données!$B$44:$L$57,4,FALSE()),0)-(COUNTIF($G$7:G7,"Commercial Junior")+COUNTIF($G$7:G7,"Commercial Senior")+COUNTIF($G$7:G7,"Directrice Commerciale"))*2-IF($B$2="Azura Commerce",1,0)+IFERROR(VLOOKUP(H8,Données!$B$2:$V$38,19,FALSE()),0)+SUMPRODUCT(IFERROR(VLOOKUP($H$7:H8,Données!$B$2:$V$38,20,FALSE()),0)))) -> 2 | L8: =IF(A8="","",L7+D8-IF(F8="Comptant",E8,0)+COUNTIF($G$7:G8,"Commercial Junior")*4+IF($B$2="Véloce Transports",COUNTIF($G$7:G8,"Commercial Senior")*6,0)+IF($B$2="Azura Commerce",2,0)+M7+IFERROR(VLOOKUP(H8,Données!$B$2:$R$33,4,FALSE()),0)+SUMPRODUCT(IFERROR(VLOOKUP($H$7:H8,Données!$B$2:$R$33,10,FALSE()),0))+IFERROR(VLOOKUP(I8,Données!$B$39:$L$52,3,FALSE()),0)-(COUNTIF($G$7:G8,"Commercial Junior")*1+COUNTIF($G$7:G8,"Commercial Senior")*2+COUNTIF($G$7:G8,"Directrice Commerciale")*3)-IF(MOD(A8-1,4)=0,MAX(1,ROUND(P7*0.05,0)),0)+IF($B$2="Synergia Lab",1,0)) -> -1 | M8: =IF(A8="","",N7+IF($B$2<>"Véloce Transports",COUNTIF($G$7:G8,"Commercial Senior")*6,0)) -> 0 | N8: =IF(A8="","",COUNTIF($G$7:G8,"Directrice Commerciale")*8+IFERROR(VLOOKUP(I8,Données!$B$39:$L$52,10,FALSE()),0)) -> 0 | O8: =IF(A8="","",O7+IF(F8="Crédit",E8,0)) -> 0 | P8: =IF(A8="","",P7+D8+IFERROR(VLOOKUP(H8,Données!$B$2:$R$33,5,FALSE()),0)) -> 0 | Q8: =IF(A8="","",Q7+IFERROR(VLOOKUP(H8,Données!$B$2:$R$33,6,FALSE()),0)) -> 0 | R8: =IF(A8="","",J8+K8+MAX(0,L8)+M8+N8) -> 2 | S8: =IF(A8="","",Q8+P8+O8+MAX(0,-L8)+T8) -> 2 | T8: =IF(A8="","",R8-Q8-P8-O8-MAX(0,-L8)) -> 1 | U8: =IF(A8="","",IF(ABS(R8-S8)<0.01,"✓","⚠")) -> ✓ | V8: =IF(A8="","",V7+COUNTIF($G$7:G7,"Commercial Junior")*4+COUNTIF($G$7:G7,"Commercial Senior")*6+COUNTIF($G$7:G7,"Directrice Commerciale")*8+IF($B$2="Azura Commerce",2,0)+IFERROR(VLOOKUP(I8,Données!$B$44:$L$57,2,FALSE()),0)) -> 0 | W8: =IF(A8="","",W7+(COUNTIF($G$7:G7,"Commercial Junior")+COUNTIF($G$7:G7,"Commercial Senior")+COUNTIF($G$7:G7,"Directrice Commerciale"))*2+IF($B$2="Azura Commerce",1,0)+IFERROR(VLOOKUP(I8,Données!$B$44:$L$57,5,FALSE()),0)+SUMPRODUCT(IFERROR(VLOOKUP($H$7:H8,Données!$B$2:$V$38,22,FALSE()),0))) -> 0 | X8: =IF(A8="","",X7+COUNTIF($G$7:G7,"Commercial Junior")*1+COUNTIF($G$7:G7,"Commercial Senior")*2+COUNTIF($G$7:G7,"Directrice Commerciale")*3+SUMPRODUCT(IFERROR(VLOOKUP($H$7:H8,Données!$B$2:$V$38,12,FALSE()),0))) -> 0 | Y8: =IF(A8="","",Y7+IF(MOD(A8-1,4)=0,MAX(1,ROUND(P7*0.05,0)),0)+SUMPRODUCT(IFERROR(VLOOKUP($H$7:H8,Données!$B$2:$V$38,11,FALSE()),0))) -> 1 | Z8: =IF(A8="","",MAX(0,Z7+MIN(J7+IFERROR(VLOOKUP(H8,Données!$B$2:$V$38,3,FALSE()),0),2+IF(IFERROR(VLOOKUP(H8,Données!$B$2:$V$38,3,FALSE()),0)>0,1,0))+SUMPRODUCT(IFERROR(VLOOKUP($H$7:H8,Données!$B$2:$V$38,21,FALSE()),0)))) -> 0 | AA8: =IF(A8="","",AA7+IFERROR(VLOOKUP(I8,Données!$B$39:$L$52,8,FALSE()),0)+SUMPRODUCT(IFERROR(VLOOKUP($H$7:H8,Données!$B$2:$R$33,13,FALSE()),0))) -> 0 | AB8: =IF(A8="","",AB7+IFERROR(VLOOKUP(I8,Données!$B$39:$L$52,6,FALSE()),0)+IFERROR(VLOOKUP(I8,Données!$B$39:$L$52,7,FALSE()),0)) -> 0 | AC8: =IF(A8="","",V8-W8-X8-Y8-Z8+AA8-AB8) -> -1 | AD8: =IF(A8="","",T8*3+J8*2+MAX(0,L8)+Q8-MAX(0,-L8)) -> 2 | AE8: =IF(A8="","",L8-L7) -> 0 | AF8: =IF(A8="","",T8-T7) -> 1 | AG8: =IF(A8="","",V8-V7) -> 0 | AH8: =IF(A8="","",W8+X8+Y8+Z8-W7-X7-Y7-Z7) -> 0
A9: =IF(A6+3<=$E$2,3,"") -> 3 | B9: =IF(A9="","",QUOTIENT(A9-1,4)+1) -> 1 | C9: =IF(A9="","",MOD(A9-1,4)+1) -> 3 | J9: =IF(A9="","",MAX(0,J8+IFERROR(VLOOKUP(H9,Données!$B$2:$R$33,3,FALSE()),0)-(2+IF(IFERROR(VLOOKUP(H9,Données!$B$2:$R$33,3,FALSE()),0)>0,1,0)))) -> 0 | K9: =IF(A9="","",MAX(0,K8+E9+IF($B$2="Manufacture Belvaux",1,0)+IFERROR(VLOOKUP(I9,Données!$B$44:$L$57,4,FALSE()),0)-(COUNTIF($G$7:G7,"Commercial Junior")+COUNTIF($G$7:G7,"Commercial Senior")+COUNTIF($G$7:G7,"Directrice Commerciale"))*2-IF($B$2="Azura Commerce",1,0)+IFERROR(VLOOKUP(H9,Données!$B$2:$V$38,19,FALSE()),0)+SUMPRODUCT(IFERROR(VLOOKUP($H$7:H9,Données!$B$2:$V$38,20,FALSE()),0)))) -> 3 | L9: =IF(A9="","",L8+D9-IF(F9="Comptant",E9,0)+COUNTIF($G$7:G9,"Commercial Junior")*4+IF($B$2="Véloce Transports",COUNTIF($G$7:G9,"Commercial Senior")*6,0)+IF($B$2="Azura Commerce",2,0)+M8+IFERROR(VLOOKUP(H9,Données!$B$2:$R$33,4,FALSE()),0)+SUMPRODUCT(IFERROR(VLOOKUP($H$7:H9,Données!$B$2:$R$33,10,FALSE()),0))+IFERROR(VLOOKUP(I9,Données!$B$39:$L$52,3,FALSE()),0)-(COUNTIF($G$7:G9,"Commercial Junior")*1+COUNTIF($G$7:G9,"Commercial Senior")*2+COUNTIF($G$7:G9,"Directrice Commerciale")*3)-IF(MOD(A9-1,4)=0,MAX(1,ROUND(P8*0.05,0)),0)+IF($B$2="Synergia Lab",1,0)) -> -1 | M9: =IF(A9="","",N8+IF($B$2<>"Véloce Transports",COUNTIF($G$7:G9,"Commercial Senior")*6,0)) -> 0 | N9: =IF(A9="","",COUNTIF($G$7:G9,"Directrice Commerciale")*8+IFERROR(VLOOKUP(I9,Données!$B$39:$L$52,10,FALSE()),0)) -> 0 | O9: =IF(A9="","",O8+IF(F9="Crédit",E9,0)) -> 0 | P9: =IF(A9="","",P8+D9+IFERROR(VLOOKUP(H9,Données!$B$2:$R$33,5,FALSE()),0)) -> 0 | Q9: =IF(A9="","",Q8+IFERROR(VLOOKUP(H9,Données!$B$2:$R$33,6,FALSE()),0)) -> 0 | R9: =IF(A9="","",J9+K9+MAX(0,L9)+M9+N9) -> 3 | S9: =IF(A9="","",Q9+P9+O9+MAX(0,-L9)+T9) -> 3 | T9: =IF(A9="","",R9-Q9-P9-O9-MAX(0,-L9)) -> 2 | U9: =IF(A9="","",IF(ABS(R9-S9)<0.01,"✓","⚠")) -> ✓ | V9: =IF(A9="","",V8+COUNTIF($G$7:G7,"Commercial Junior")*4+COUNTIF($G$7:G7,"Commercial Senior")*6+COUNTIF($G$7:G7,"Directrice Commerciale")*8+IF($B$2="Azura Commerce",2,0)+IFERROR(VLOOKUP(I9,Données!$B$44:$L$57,2,FALSE()),0)) -> 0 | W9: =IF(A9="","",W8+(COUNTIF($G$7:G7,"Commercial Junior")+COUNTIF($G$7:G7,"Commercial Senior")+COUNTIF($G$7:G7,"Directrice Commerciale"))*2+IF($B$2="Azura Commerce",1,0)+IFERROR(VLOOKUP(I9,Données!$B$44:$L$57,5,FALSE()),0)+SUMPRODUCT(IFERROR(VLOOKUP($H$7:H9,Données!$B$2:$V$38,22,FALSE()),0))) -> 0 | X9: =IF(A9="","",X8+COUNTIF($G$7:G7,"Commercial Junior")*1+COUNTIF($G$7:G7,"Commercial Senior")*2+COUNTIF($G$7:G7,"Directrice Commerciale")*3+SUMPRODUCT(IFERROR(VLOOKUP($H$7:H9,Données!$B$2:$V$38,12,FALSE()),0))) -> 0 | Y9: =IF(A9="","",Y8+IF(MOD(A9-1,4)=0,MAX(1,ROUND(P8*0.05,0)),0)+SUMPRODUCT(IFERROR(VLOOKUP($H$7:H9,Données!$B$2:$V$38,11,FALSE()),0))) -> 1 | Z9: =IF(A9="","",MAX(0,Z8+MIN(J8+IFERROR(VLOOKUP(H9,Données!$B$2:$V$38,3,FALSE()),0),2+IF(IFERROR(VLOOKUP(H9,Données!$B$2:$V$38,3,FALSE()),0)>0,1,0))+SUMPRODUCT(IFERROR(VLOOKUP($H$7:H9,Données!$B$2:$V$38,21,FALSE()),0)))) -> 0 | AA9: =IF(A9="","",AA8+IFERROR(VLOOKUP(I9,Données!$B$39:$L$52,8,FALSE()),0)+SUMPRODUCT(IFERROR(VLOOKUP($H$7:H9,Données!$B$2:$R$33,13,FALSE()),0))) -> 0 | AB9: =IF(A9="","",AB8+IFERROR(VLOOKUP(I9,Données!$B$39:$L$52,6,FALSE()),0)+IFERROR(VLOOKUP(I9,Données!$B$39:$L$52,7,FALSE()),0)) -> 0 | AC9: =IF(A9="","",V9-W9-X9-Y9-Z9+AA9-AB9) -> -1 | AD9: =IF(A9="","",T9*3+J9*2+MAX(0,L9)+Q9-MAX(0,-L9)) -> 5 | AE9: =IF(A9="","",L9-L8) -> 0 | AF9: =IF(A9="","",T9-T8) -> 1 | AG9: =IF(A9="","",V9-V8) -> 0 | AH9: =IF(A9="","",W9+X9+Y9+Z9-W8-X8-Y8-Z8) -> 0
A10: =IF(A6+4<=$E$2,4,"") -> 4 | B10: =IF(A10="","",QUOTIENT(A10-1,4)+1) -> 1 | C10: =IF(A10="","",MOD(A10-1,4)+1) -> 4 | J10: =IF(A10="","",MAX(0,J9+IFERROR(VLOOKUP(H10,Données!$B$2:$R$33,3,FALSE()),0)-(2+IF(IFERROR(VLOOKUP(H10,Données!$B$2:$R$33,3,FALSE()),0)>0,1,0)))) -> 0 | K10: =IF(A10="","",MAX(0,K9+E10+IF($B$2="Manufacture Belvaux",1,0)+IFERROR(VLOOKUP(I10,Données!$B$44:$L$57,4,FALSE()),0)-(COUNTIF($G$7:G7,"Commercial Junior")+COUNTIF($G$7:G7,"Commercial Senior")+COUNTIF($G$7:G7,"Directrice Commerciale"))*2-IF($B$2="Azura Commerce",1,0)+IFERROR(VLOOKUP(H10,Données!$B$2:$V$38,19,FALSE()),0)+SUMPRODUCT(IFERROR(VLOOKUP($H$7:H10,Données!$B$2:$V$38,20,FALSE()),0)))) -> 4 | L10: =IF(A10="","",L9+D10-IF(F10="Comptant",E10,0)+COUNTIF($G$7:G10,"Commercial Junior")*4+IF($B$2="Véloce Transports",COUNTIF($G$7:G10,"Commercial Senior")*6,0)+IF($B$2="Azura Commerce",2,0)+M9+IFERROR(VLOOKUP(H10,Données!$B$2:$R$33,4,FALSE()),0)+SUMPRODUCT(IFERROR(VLOOKUP($H$7:H10,Données!$B$2:$R$33,10,FALSE()),0))+IFERROR(VLOOKUP(I10,Données!$B$39:$L$52,3,FALSE()),0)-(COUNTIF($G$7:G10,"Commercial Junior")*1+COUNTIF($G$7:G10,"Commercial Senior")*2+COUNTIF($G$7:G10,"Directrice Commerciale")*3)-IF(MOD(A10-1,4)=0,MAX(1,ROUND(P9*0.05,0)),0)+IF($B$2="Synergia Lab",1,0)) -> -1 | M10: =IF(A10="","",N9+IF($B$2<>"Véloce Transports",COUNTIF($G$7:G10,"Commercial Senior")*6,0)) -> 0 | N10: =IF(A10="","",COUNTIF($G$7:G10,"Directrice Commerciale")*8+IFERROR(VLOOKUP(I10,Données!$B$39:$L$52,10,FALSE()),0)) -> 0 | O10: =IF(A10="","",O9+IF(F10="Crédit",E10,0)) -> 0 | P10: =IF(A10="","",P9+D10+IFERROR(VLOOKUP(H10,Données!$B$2:$R$33,5,FALSE()),0)) -> 0 | Q10: =IF(A10="","",Q9+IFERROR(VLOOKUP(H10,Données!$B$2:$R$33,6,FALSE()),0)) -> 0 | R10: =IF(A10="","",J10+K10+MAX(0,L10)+M10+N10) -> 4 | S10: =IF(A10="","",Q10+P10+O10+MAX(0,-L10)+T10) -> 4 | T10: =IF(A10="","",R10-Q10-P10-O10-MAX(0,-L10)) -> 3 | U10: =IF(A10="","",IF(ABS(R10-S10)<0.01,"✓","⚠")) -> ✓ | V10: =IF(A10="","",V9+COUNTIF($G$7:G7,"Commercial Junior")*4+COUNTIF($G$7:G7,"Commercial Senior")*6+COUNTIF($G$7:G7,"Directrice Commerciale")*8+IF($B$2="Azura Commerce",2,0)+IFERROR(VLOOKUP(I10,Données!$B$44:$L$57,2,FALSE()),0)) -> 0 | W10: =IF(A10="","",W9+(COUNTIF($G$7:G7,"Commercial Junior")+COUNTIF($G$7:G7,"Commercial Senior")+COUNTIF($G$7:G7,"Directrice Commerciale"))*2+IF($B$2="Azura Commerce",1,0)+IFERROR(VLOOKUP(I10,Données!$B$44:$L$57,5,FALSE()),0)+SUMPRODUCT(IFERROR(VLOOKUP($H$7:H10,Données!$B$2:$V$38,22,FALSE()),0))) -> 0 | X10: =IF(A10="","",X9+COUNTIF($G$7:G7,"Commercial Junior")*1+COUNTIF($G$7:G7,"Commercial Senior")*2+COUNTIF($G$7:G7,"Directrice Commerciale")*3+SUMPRODUCT(IFERROR(VLOOKUP($H$7:H10,Données!$B$2:$V$38,12,FALSE()),0))) -> 0 | Y10: =IF(A10="","",Y9+IF(MOD(A10-1,4)=0,MAX(1,ROUND(P9*0.05,0)),0)+SUMPRODUCT(IFERROR(VLOOKUP($H$7:H10,Données!$B$2:$V$38,11,FALSE()),0))) -> 1 | Z10: =IF(A10="","",MAX(0,Z9+MIN(J9+IFERROR(VLOOKUP(H10,Données!$B$2:$V$38,3,FALSE()),0),2+IF(IFERROR(VLOOKUP(H10,Données!$B$2:$V$38,3,FALSE()),0)>0,1,0))+SUMPRODUCT(IFERROR(VLOOKUP($H$7:H10,Données!$B$2:$V$38,21,FALSE()),0)))) -> 0 | AA10: =IF(A10="","",AA9+IFERROR(VLOOKUP(I10,Données!$B$39:$L$52,8,FALSE()),0)+SUMPRODUCT(IFERROR(VLOOKUP($H$7:H10,Données!$B$2:$R$33,13,FALSE()),0))) -> 0 | AB10: =IF(A10="","",AB9+IFERROR(VLOOKUP(I10,Données!$B$39:$L$52,6,FALSE()),0)+IFERROR(VLOOKUP(I10,Données!$B$39:$L$52,7,FALSE()),0)) -> 0 | AC10: =IF(A10="","",V10-W10-X10-Y10-Z10+AA10-AB10) -> -1 | AD10: =IF(A10="","",T10*3+J10*2+MAX(0,L10)+Q10-MAX(0,-L10)) -> 8 | AE10: =IF(A10="","",L10-L9) -> 0 | AF10: =IF(A10="","",T10-T9) -> 1 | AG10: =IF(A10="","",V10-V9) -> 0 | AH10: =IF(A10="","",W10+X10+Y10+Z10-W9-X9-Y9-Z9) -> 0
A11: =IF(A6+5<=$E$2,5,"") -> 5 | B11: =IF(A11="","",QUOTIENT(A11-1,4)+1) -> 2 | C11: =IF(A11="","",MOD(A11-1,4)+1) -> 1 | J11: =IF(A11="","",MAX(0,J10+IFERROR(VLOOKUP(H11,Données!$B$2:$R$33,3,FALSE()),0)-(2+IF(IFERROR(VLOOKUP(H11,Données!$B$2:$R$33,3,FALSE()),0)>0,1,0)))) -> 0 | K11: =IF(A11="","",MAX(0,K10+E11+IF($B$2="Manufacture Belvaux",1,0)+IFERROR(VLOOKUP(I11,Données!$B$44:$L$57,4,FALSE()),0)-(COUNTIF($G$7:G7,"Commercial Junior")+COUNTIF($G$7:G7,"Commercial Senior")+COUNTIF($G$7:G7,"Directrice Commerciale"))*2-IF($B$2="Azura Commerce",1,0)+IFERROR(VLOOKUP(H11,Données!$B$2:$V$38,19,FALSE()),0)+SUMPRODUCT(IFERROR(VLOOKUP($H$7:H11,Données!$B$2:$V$38,20,FALSE()),0)))) -> 5 | L11: =IF(A11="","",L10+D11-IF(F11="Comptant",E11,0)+COUNTIF($G$7:G11,"Commercial Junior")*4+IF($B$2="Véloce Transports",COUNTIF($G$7:G11,"Commercial Senior")*6,0)+IF($B$2="Azura Commerce",2,0)+M10+IFERROR(VLOOKUP(H11,Données!$B$2:$R$33,4,FALSE()),0)+SUMPRODUCT(IFERROR(VLOOKUP($H$7:H11,Données!$B$2:$R$33,10,FALSE()),0))+IFERROR(VLOOKUP(I11,Données!$B$39:$L$52,3,FALSE()),0)-(COUNTIF($G$7:G11,"Commercial Junior")*1+COUNTIF($G$7:G11,"Commercial Senior")*2+COUNTIF($G$7:G11,"Directrice Commerciale")*3)-IF(MOD(A11-1,4)=0,MAX(1,ROUND(P10*0.05,0)),0)+IF($B$2="Synergia Lab",1,0)) -> -2 | M11: =IF(A11="","",N10+IF($B$2<>"Véloce Transports",COUNTIF($G$7:G11,"Commercial Senior")*6,0)) -> 0 | N11: =IF(A11="","",COUNTIF($G$7:G11,"Directrice Commerciale")*8+IFERROR(VLOOKUP(I11,Données!$B$39:$L$52,10,FALSE()),0)) -> 0 | O11: =IF(A11="","",O10+IF(F11="Crédit",E11,0)) -> 0 | P11: =IF(A11="","",P10+D11+IFERROR(VLOOKUP(H11,Données!$B$2:$R$33,5,FALSE()),0)) -> 0 | Q11: =IF(A11="","",Q10+IFERROR(VLOOKUP(H11,Données!$B$2:$R$33,6,FALSE()),0)) -> 0 | R11: =IF(A11="","",J11+K11+MAX(0,L11)+M11+N11) -> 5 | S11: =IF(A11="","",Q11+P11+O11+MAX(0,-L11)+T11) -> 5 | T11: =IF(A11="","",R11-Q11-P11-O11-MAX(0,-L11)) -> 3 | U11: =IF(A11="","",IF(ABS(R11-S11)<0.01,"✓","⚠")) -> ✓ | V11: =IF(A11="","",V10+COUNTIF($G$7:G7,"Commercial Junior")*4+COUNTIF($G$7:G7,"Commercial Senior")*6+COUNTIF($G$7:G7,"Directrice Commerciale")*8+IF($B$2="Azura Commerce",2,0)+IFERROR(VLOOKUP(I11,Données!$B$44:$L$57,2,FALSE()),0)) -> 0 | W11: =IF(A11="","",W10+(COUNTIF($G$7:G7,"Commercial Junior")+COUNTIF($G$7:G7,"Commercial Senior")+COUNTIF($G$7:G7,"Directrice Commerciale"))*2+IF($B$2="Azura Commerce",1,0)+IFERROR(VLOOKUP(I11,Données!$B$44:$L$57,5,FALSE()),0)+SUMPRODUCT(IFERROR(VLOOKUP($H$7:H11,Données!$B$2:$V$38,22,FALSE()),0))) -> 0 | X11: =IF(A11="","",X10+COUNTIF($G$7:G7,"Commercial Junior")*1+COUNTIF($G$7:G7,"Commercial Senior")*2+COUNTIF($G$7:G7,"Directrice Commerciale")*3+SUMPRODUCT(IFERROR(VLOOKUP($H$7:H11,Données!$B$2:$V$38,12,FALSE()),0))) -> 0 | Y11: =IF(A11="","",Y10+IF(MOD(A11-1,4)=0,MAX(1,ROUND(P10*0.05,0)),0)+SUMPRODUCT(IFERROR(VLOOKUP($H$7:H11,Données!$B$2:$V$38,11,FALSE()),0))) -> 2 | Z11: =IF(A11="","",MAX(0,Z10+MIN(J10+IFERROR(VLOOKUP(H11,Données!$B$2:$V$38,3,FALSE()),0),2+IF(IFERROR(VLOOKUP(H11,Données!$B$2:$V$38,3,FALSE()),0)>0,1,0))+SUMPRODUCT(IFERROR(VLOOKUP($H$7:H11,Données!$B$2:$V$38,21,FALSE()),0)))) -> 0 | AA11: =IF(A11="","",AA10+IFERROR(VLOOKUP(I11,Données!$B$39:$L$52,8,FALSE()),0)+SUMPRODUCT(IFERROR(VLOOKUP($H$7:H11,Données!$B$2:$R$33,13,FALSE()),0))) -> 0 | AB11: =IF(A11="","",AB10+IFERROR(VLOOKUP(I11,Données!$B$39:$L$52,6,FALSE()),0)+IFERROR(VLOOKUP(I11,Données!$B$39:$L$52,7,FALSE()),0)) -> 0 | AC11: =IF(A11="","",V11-W11-X11-Y11-Z11+AA11-AB11) -> -2 | AD11: =IF(A11="","",T11*3+J11*2+MAX(0,L11)+Q11-MAX(0,-L11)) -> 7 | AE11: =IF(A11="","",L11-L10) -> -1 | AF11: =IF(A11="","",T11-T10) -> 0 | AG11: =IF(A11="","",V11-V10) -> 0 | AH11: =IF(A11="","",W11+X11+Y11+Z11-W10-X10-Y10-Z10) -> 1
A12: =IF(A6+6<=$E$2,6,"") -> 6 | B12: =IF(A12="","",QUOTIENT(A12-1,4)+1) -> 2 | C12: =IF(A12="","",MOD(A12-1,4)+1) -> 2 | J12: =IF(A12="","",MAX(0,J11+IFERROR(VLOOKUP(H12,Données!$B$2:$R$33,3,FALSE()),0)-(2+IF(IFERROR(VLOOKUP(H12,Données!$B$2:$R$33,3,FALSE()),0)>0,1,0)))) -> 0 | K12: =IF(A12="","",MAX(0,K11+E12+IF($B$2="Manufacture Belvaux",1,0)+IFERROR(VLOOKUP(I12,Données!$B$44:$L$57,4,FALSE()),0)-(COUNTIF($G$7:G7,"Commercial Junior")+COUNTIF($G$7:G7,"Commercial Senior")+COUNTIF($G$7:G7,"Directrice Commerciale"))*2-IF($B$2="Azura Commerce",1,0)+IFERROR(VLOOKUP(H12,Données!$B$2:$V$38,19,FALSE()),0)+SUMPRODUCT(IFERROR(VLOOKUP($H$7:H12,Données!$B$2:$V$38,20,FALSE()),0)))) -> 6 | L12: =IF(A12="","",L11+D12-IF(F12="Comptant",E12,0)+COUNTIF($G$7:G12,"Commercial Junior")*4+IF($B$2="Véloce Transports",COUNTIF($G$7:G12,"Commercial Senior")*6,0)+IF($B$2="Azura Commerce",2,0)+M11+IFERROR(VLOOKUP(H12,Données!$B$2:$R$33,4,FALSE()),0)+SUMPRODUCT(IFERROR(VLOOKUP($H$7:H12,Données!$B$2:$R$33,10,FALSE()),0))+IFERROR(VLOOKUP(I12,Données!$B$39:$L$52,3,FALSE()),0)-(COUNTIF($G$7:G12,"Commercial Junior")*1+COUNTIF($G$7:G12,"Commercial Senior")*2+COUNTIF($G$7:G12,"Directrice Commerciale")*3)-IF(MOD(A12-1,4)=0,MAX(1,ROUND(P11*0.05,0)),0)+IF($B$2="Synergia Lab",1,0)) -> -2 | M12: =IF(A12="","",N11+IF($B$2<>"Véloce Transports",COUNTIF($G$7:G12,"Commercial Senior")*6,0)) -> 0 | N12: =IF(A12="","",COUNTIF($G$7:G12,"Directrice Commerciale")*8+IFERROR(VLOOKUP(I12,Données!$B$39:$L$52,10,FALSE()),0)) -> 0 | O12: =IF(A12="","",O11+IF(F12="Crédit",E12,0)) -> 0 | P12: =IF(A12="","",P11+D12+IFERROR(VLOOKUP(H12,Données!$B$2:$R$33,5,FALSE()),0)) -> 0 | Q12: =IF(A12="","",Q11+IFERROR(VLOOKUP(H12,Données!$B$2:$R$33,6,FALSE()),0)) -> 0 | R12: =IF(A12="","",J12+K12+MAX(0,L12)+M12+N12) -> 6 | S12: =IF(A12="","",Q12+P12+O12+MAX(0,-L12)+T12) -> 6 | T12: =IF(A12="","",R12-Q12-P12-O12-MAX(0,-L12)) -> 4 | U12: =IF(A12="","",IF(ABS(R12-S12)<0.01,"✓","⚠")) -> ✓ | V12: =IF(A12="","",V11+COUNTIF($G$7:G7,"Commercial Junior")*4+COUNTIF($G$7:G7,"Commercial Senior")*6+COUNTIF($G$7:G7,"Directrice Commerciale")*8+IF($B$2="Azura Commerce",2,0)+IFERROR(VLOOKUP(I12,Données!$B$44:$L$57,2,FALSE()),0)) -> 0 | W12: =IF(A12="","",W11+(COUNTIF($G$7:G7,"Commercial Junior")+COUNTIF($G$7:G7,"Commercial Senior")+COUNTIF($G$7:G7,"Directrice Commerciale"))*2+IF($B$2="Azura Commerce",1,0)+IFERROR(VLOOKUP(I12,Données!$B$44:$L$57,5,FALSE()),0)+SUMPRODUCT(IFERROR(VLOOKUP($H$7:H12,Données!$B$2:$V$38,22,FALSE()),0))) -> 0 | X12: =IF(A12="","",X11+COUNTIF($G$7:G7,"Commercial Junior")*1+COUNTIF($G$7:G7,"Commercial Senior")*2+COUNTIF($G$7:G7,"Directrice Commerciale")*3+SUMPRODUCT(IFERROR(VLOOKUP($H$7:H12,Données!$B$2:$V$38,12,FALSE()),0))) -> 0 | Y12: =IF(A12="","",Y11+IF(MOD(A12-1,4)=0,MAX(1,ROUND(P11*0.05,0)),0)+SUMPRODUCT(IFERROR(VLOOKUP($H$7:H12,Données!$B$2:$V$38,11,FALSE()),0))) -> 2 | Z12: =IF(A12="","",MAX(0,Z11+MIN(J11+IFERROR(VLOOKUP(H12,Données!$B$2:$V$38,3,FALSE()),0),2+IF(IFERROR(VLOOKUP(H12,Données!$B$2:$V$38,3,FALSE()),0)>0,1,0))+SUMPRODUCT(IFERROR(VLOOKUP($H$7:H12,Données!$B$2:$V$38,21,FALSE()),0)))) -> 0 | AA12: =IF(A12="","",AA11+IFERROR(VLOOKUP(I12,Données!$B$39:$L$52,8,FALSE()),0)+SUMPRODUCT(IFERROR(VLOOKUP($H$7:H12,Données!$B$2:$R$33,13,FALSE()),0))) -> 0 | AB12: =IF(A12="","",AB11+IFERROR(VLOOKUP(I12,Données!$B$39:$L$52,6,FALSE()),0)+IFERROR(VLOOKUP(I12,Données!$B$39:$L$52,7,FALSE()),0)) -> 0 | AC12: =IF(A12="","",V12-W12-X12-Y12-Z12+AA12-AB12) -> -2 | AD12: =IF(A12="","",T12*3+J12*2+MAX(0,L12)+Q12-MAX(0,-L12)) -> 10 | AE12: =IF(A12="","",L12-L11) -> 0 | AF12: =IF(A12="","",T12-T11) -> 1 | AG12: =IF(A12="","",V12-V11) -> 0 | AH12: =IF(A12="","",W12+X12+Y12+Z12-W11-X11-Y11-Z11) -> 0
A13: =IF(A6+7<=$E$2,7,"") | B13: =IF(A13="","",QUOTIENT(A13-1,4)+1) | C13: =IF(A13="","",MOD(A13-1,4)+1) | J13: =IF(A13="","",MAX(0,J12+IFERROR(VLOOKUP(H13,Données!$B$2:$R$33,3,FALSE()),0)-(2+IF(IFERROR(VLOOKUP(H13,Données!$B$2:$R$33,3,FALSE()),0)>0,1,0)))) | K13: =IF(A13="","",MAX(0,K12+E13+IF($B$2="Manufacture Belvaux",1,0)+IFERROR(VLOOKUP(I13,Données!$B$44:$L$57,4,FALSE()),0)-(COUNTIF($G$7:G7,"Commercial Junior")+COUNTIF($G$7:G7,"Commercial Senior")+COUNTIF($G$7:G7,"Directrice Commerciale"))*2-IF($B$2="Azura Commerce",1,0)+IFERROR(VLOOKUP(H13,Données!$B$2:$V$38,19,FALSE()),0)+SUMPRODUCT(IFERROR(VLOOKUP($H$7:H13,Données!$B$2:$V$38,20,FALSE()),0)))) | L13: =IF(A13="","",L12+D13-IF(F13="Comptant",E13,0)+COUNTIF($G$7:G13,"Commercial Junior")*4+IF($B$2="Véloce Transports",COUNTIF($G$7:G13,"Commercial Senior")*6,0)+IF($B$2="Azura Commerce",2,0)+M12+IFERROR(VLOOKUP(H13,Données!$B$2:$R$33,4,FALSE()),0)+SUMPRODUCT(IFERROR(VLOOKUP($H$7:H13,Données!$B$2:$R$33,10,FALSE()),0))+IFERROR(VLOOKUP(I13,Données!$B$39:$L$52,3,FALSE()),0)-(COUNTIF($G$7:G13,"Commercial Junior")*1+COUNTIF($G$7:G13,"Commercial Senior")*2+COUNTIF($G$7:G13,"Directrice Commerciale")*3)-IF(MOD(A13-1,4)=0,MAX(1,ROUND(P12*0.05,0)),0)+IF($B$2="Synergia Lab",1,0)) | M13: =IF(A13="","",N12+IF($B$2<>"Véloce Transports",COUNTIF($G$7:G13,"Commercial Senior")*6,0)) | N13: =IF(A13="","",COUNTIF($G$7:G13,"Directrice Commerciale")*8+IFERROR(VLOOKUP(I13,Données!$B$39:$L$52,10,FALSE()),0)) | O13: =IF(A13="","",O12+IF(F13="Crédit",E13,0)) | P13: =IF(A13="","",P12+D13+IFERROR(VLOOKUP(H13,Données!$B$2:$R$33,5,FALSE()),0)) | Q13: =IF(A13="","",Q12+IFERROR(VLOOKUP(H13,Données!$B$2:$R$33,6,FALSE()),0)) | R13: =IF(A13="","",J13+K13+MAX(0,L13)+M13+N13) | S13: =IF(A13="","",Q13+P13+O13+MAX(0,-L13)+T13) | T13: =IF(A13="","",R13-Q13-P13-O13-MAX(0,-L13)) | U13: =IF(A13="","",IF(ABS(R13-S13)<0.01,"✓","⚠")) | V13: =IF(A13="","",V12+COUNTIF($G$7:G7,"Commercial Junior")*4+COUNTIF($G$7:G7,"Commercial Senior")*6+COUNTIF($G$7:G7,"Directrice Commerciale")*8+IF($B$2="Azura Commerce",2,0)+IFERROR(VLOOKUP(I13,Données!$B$44:$L$57,2,FALSE()),0)) | W13: =IF(A13="","",W12+(COUNTIF($G$7:G7,"Commercial Junior")+COUNTIF($G$7:G7,"Commercial Senior")+COUNTIF($G$7:G7,"Directrice Commerciale"))*2+IF($B$2="Azura Commerce",1,0)+IFERROR(VLOOKUP(I13,Données!$B$44:$L$57,5,FALSE()),0)+SUMPRODUCT(IFERROR(VLOOKUP($H$7:H13,Données!$B$2:$V$38,22,FALSE()),0))) | X13: =IF(A13="","",X12+COUNTIF($G$7:G7,"Commercial Junior")*1+COUNTIF($G$7:G7,"Commercial Senior")*2+COUNTIF($G$7:G7,"Directrice Commerciale")*3+SUMPRODUCT(IFERROR(VLOOKUP($H$7:H13,Données!$B$2:$V$38,12,FALSE()),0))) | Y13: =IF(A13="","",Y12+IF(MOD(A13-1,4)=0,MAX(1,ROUND(P12*0.05,0)),0)+SUMPRODUCT(IFERROR(VLOOKUP($H$7:H13,Données!$B$2:$V$38,11,FALSE()),0))) | Z13: =IF(A13="","",MAX(0,Z12+MIN(J12+IFERROR(VLOOKUP(H13,Données!$B$2:$V$38,3,FALSE()),0),2+IF(IFERROR(VLOOKUP(H13,Données!$B$2:$V$38,3,FALSE()),0)>0,1,0))+SUMPRODUCT(IFERROR(VLOOKUP($H$7:H13,Données!$B$2:$V$38,21,FALSE()),0)))) | AA13: =IF(A13="","",AA12+IFERROR(VLOOKUP(I13,Données!$B$39:$L$52,8,FALSE()),0)+SUMPRODUCT(IFERROR(VLOOKUP($H$7:H13,Données!$B$2:$R$33,13,FALSE()),0))) | AB13: =IF(A13="","",AB12+IFERROR(VLOOKUP(I13,Données!$B$39:$L$52,6,FALSE()),0)+IFERROR(VLOOKUP(I13,Données!$B$39:$L$52,7,FALSE()),0)) | AC13: =IF(A13="","",V13-W13-X13-Y13-Z13+AA13-AB13) | AD13: =IF(A13="","",T13*3+J13*2+MAX(0,L13)+Q13-MAX(0,-L13)) | AE13: =IF(A13="","",L13-L12) | AF13: =IF(A13="","",T13-T12) | AG13: =IF(A13="","",V13-V12) | AH13: =IF(A13="","",W13+X13+Y13+Z13-W12-X12-Y12-Z12)
A14: =IF(A6+8<=$E$2,8,"") | B14: =IF(A14="","",QUOTIENT(A14-1,4)+1) | C14: =IF(A14="","",MOD(A14-1,4)+1) | J14: =IF(A14="","",MAX(0,J13+IFERROR(VLOOKUP(H14,Données!$B$2:$R$33,3,FALSE()),0)-(2+IF(IFERROR(VLOOKUP(H14,Données!$B$2:$R$33,3,FALSE()),0)>0,1,0)))) | K14: =IF(A14="","",MAX(0,K13+E14+IF($B$2="Manufacture Belvaux",1,0)+IFERROR(VLOOKUP(I14,Données!$B$44:$L$57,4,FALSE()),0)-(COUNTIF($G$7:G7,"Commercial Junior")+COUNTIF($G$7:G7,"Commercial Senior")+COUNTIF($G$7:G7,"Directrice Commerciale"))*2-IF($B$2="Azura Commerce",1,0)+IFERROR(VLOOKUP(H14,Données!$B$2:$V$38,19,FALSE()),0)+SUMPRODUCT(IFERROR(VLOOKUP($H$7:H14,Données!$B$2:$V$38,20,FALSE()),0)))) | L14: =IF(A14="","",L13+D14-IF(F14="Comptant",E14,0)+COUNTIF($G$7:G14,"Commercial Junior")*4+IF($B$2="Véloce Transports",COUNTIF($G$7:G14,"Commercial Senior")*6,0)+IF($B$2="Azura Commerce",2,0)+M13+IFERROR(VLOOKUP(H14,Données!$B$2:$R$33,4,FALSE()),0)+SUMPRODUCT(IFERROR(VLOOKUP($H$7:H14,Données!$B$2:$R$33,10,FALSE()),0))+IFERROR(VLOOKUP(I14,Données!$B$39:$L$52,3,FALSE()),0)-(COUNTIF($G$7:G14,"Commercial Junior")*1+COUNTIF($G$7:G14,"Commercial Senior")*2+COUNTIF($G$7:G14,"Directrice Commerciale")*3)-IF(MOD(A14-1,4)=0,MAX(1,ROUND(P13*0.05,0)),0)+IF($B$2="Synergia Lab",1,0)) | M14: =IF(A14="","",N13+IF($B$2<>"Véloce Transports",COUNTIF($G$7:G14,"Commercial Senior")*6,0)) | N14: =IF(A14="","",COUNTIF($G$7:G14,"Directrice Commerciale")*8+IFERROR(VLOOKUP(I14,Données!$B$39:$L$52,10,FALSE()),0)) | O14: =IF(A14="","",O13+IF(F14="Crédit",E14,0)) | P14: =IF(A14="","",P13+D14+IFERROR(VLOOKUP(H14,Données!$B$2:$R$33,5,FALSE()),0)) | Q14: =IF(A14="","",Q13+IFERROR(VLOOKUP(H14,Données!$B$2:$R$33,6,FALSE()),0)) | R14: =IF(A14="","",J14+K14+MAX(0,L14)+M14+N14) | S14: =IF(A14="","",Q14+P14+O14+MAX(0,-L14)+T14) | T14: =IF(A14="","",R14-Q14-P14-O14-MAX(0,-L14)) | U14: =IF(A14="","",IF(ABS(R14-S14)<0.01,"✓","⚠")) | V14: =IF(A14="","",V13+COUNTIF($G$7:G7,"Commercial Junior")*4+COUNTIF($G$7:G7,"Commercial Senior")*6+COUNTIF($G$7:G7,"Directrice Commerciale")*8+IF($B$2="Azura Commerce",2,0)+IFERROR(VLOOKUP(I14,Données!$B$44:$L$57,2,FALSE()),0)) | W14: =IF(A14="","",W13+(COUNTIF($G$7:G7,"Commercial Junior")+COUNTIF($G$7:G7,"Commercial Senior")+COUNTIF($G$7:G7,"Directrice Commerciale"))*2+IF($B$2="Azura Commerce",1,0)+IFERROR(VLOOKUP(I14,Données!$B$44:$L$57,5,FALSE()),0)+SUMPRODUCT(IFERROR(VLOOKUP($H$7:H14,Données!$B$2:$V$38,22,FALSE()),0))) | X14: =IF(A14="","",X13+COUNTIF($G$7:G7,"Commercial Junior")*1+COUNTIF($G$7:G7,"Commercial Senior")*2+COUNTIF($G$7:G7,"Directrice Commerciale")*3+SUMPRODUCT(IFERROR(VLOOKUP($H$7:H14,Données!$B$2:$V$38,12,FALSE()),0))) | Y14: =IF(A14="","",Y13+IF(MOD(A14-1,4)=0,MAX(1,ROUND(P13*0.05,0)),0)+SUMPRODUCT(IFERROR(VLOOKUP($H$7:H14,Données!$B$2:$V$38,11,FALSE()),0))) | Z14: =IF(A14="","",MAX(0,Z13+MIN(J13+IFERROR(VLOOKUP(H14,Données!$B$2:$V$38,3,FALSE()),0),2+IF(IFERROR(VLOOKUP(H14,Données!$B$2:$V$38,3,FALSE()),0)>0,1,0))+SUMPRODUCT(IFERROR(VLOOKUP($H$7:H14,Données!$B$2:$V$38,21,FALSE()),0)))) | AA14: =IF(A14="","",AA13+IFERROR(VLOOKUP(I14,Données!$B$39:$L$52,8,FALSE()),0)+SUMPRODUCT(IFERROR(VLOOKUP($H$7:H14,Données!$B$2:$R$33,13,FALSE()),0))) | AB14: =IF(A14="","",AB13+IFERROR(VLOOKUP(I14,Données!$B$39:$L$52,6,FALSE()),0)+IFERROR(VLOOKUP(I14,Données!$B$39:$L$52,7,FALSE()),0)) | AC14: =IF(A14="","",V14-W14-X14-Y14-Z14+AA14-AB14) | AD14: =IF(A14="","",T14*3+J14*2+MAX(0,L14)+Q14-MAX(0,-L14)) | AE14: =IF(A14="","",L14-L13) | AF14: =IF(A14="","",T14-T13) | AG14: =IF(A14="","",V14-V13) | AH14: =IF(A14="","",W14+X14+Y14+Z14-W13-X13-Y13-Z13)
A15: =IF(A6+9<=$E$2,9,"") | B15: =IF(A15="","",QUOTIENT(A15-1,4)+1) | C15: =IF(A15="","",MOD(A15-1,4)+1) | J15: =IF(A15="","",MAX(0,J14+IFERROR(VLOOKUP(H15,Données!$B$2:$R$33,3,FALSE()),0)-(2+IF(IFERROR(VLOOKUP(H15,Données!$B$2:$R$33,3,FALSE()),0)>0,1,0)))) | K15: =IF(A15="","",MAX(0,K14+E15+IF($B$2="Manufacture Belvaux",1,0)+IFERROR(VLOOKUP(I15,Données!$B$44:$L$57,4,FALSE()),0)-(COUNTIF($G$7:G7,"Commercial Junior")+COUNTIF($G$7:G7,"Commercial Senior")+COUNTIF($G$7:G7,"Directrice Commerciale"))*2-IF($B$2="Azura Commerce",1,0)+IFERROR(VLOOKUP(H15,Données!$B$2:$V$38,19,FALSE()),0)+SUMPRODUCT(IFERROR(VLOOKUP($H$7:H15,Données!$B$2:$V$38,20,FALSE()),0)))) | L15: =IF(A15="","",L14+D15-IF(F15="Comptant",E15,0)+COUNTIF($G$7:G15,"Commercial Junior")*4+IF($B$2="Véloce Transports",COUNTIF($G$7:G15,"Commercial Senior")*6,0)+IF($B$2="Azura Commerce",2,0)+M14+IFERROR(VLOOKUP(H15,Données!$B$2:$R$33,4,FALSE()),0)+SUMPRODUCT(IFERROR(VLOOKUP($H$7:H15,Données!$B$2:$R$33,10,FALSE()),0))+IFERROR(VLOOKUP(I15,Données!$B$39:$L$52,3,FALSE()),0)-(COUNTIF($G$7:G15,"Commercial Junior")*1+COUNTIF($G$7:G15,"Commercial Senior")*2+COUNTIF($G$7:G15,"Directrice Commerciale")*3)-IF(MOD(A15-1,4)=0,MAX(1,ROUND(P14*0.05,0)),0)+IF($B$2="Synergia Lab",1,0)) | M15: =IF(A15="","",N14+IF($B$2<>"Véloce Transports",COUNTIF($G$7:G15,"Commercial Senior")*6,0)) | N15: =IF(A15="","",COUNTIF($G$7:G15,"Directrice Commerciale")*8+IFERROR(VLOOKUP(I15,Données!$B$39:$L$52,10,FALSE()),0)) | O15: =IF(A15="","",O14+IF(F15="Crédit",E15,0)) | P15: =IF(A15="","",P14+D15+IFERROR(VLOOKUP(H15,Données!$B$2:$R$33,5,FALSE()),0)) | Q15: =IF(A15="","",Q14+IFERROR(VLOOKUP(H15,Données!$B$2:$R$33,6,FALSE()),0)) | R15: =IF(A15="","",J15+K15+MAX(0,L15)+M15+N15) | S15: =IF(A15="","",Q15+P15+O15+MAX(0,-L15)+T15) | T15: =IF(A15="","",R15-Q15-P15-O15-MAX(0,-L15)) | U15: =IF(A15="","",IF(ABS(R15-S15)<0.01,"✓","⚠")) | V15: =IF(A15="","",V14+COUNTIF($G$7:G7,"Commercial Junior")*4+COUNTIF($G$7:G7,"Commercial Senior")*6+COUNTIF($G$7:G7,"Directrice Commerciale")*8+IF($B$2="Azura Commerce",2,0)+IFERROR(VLOOKUP(I15,Données!$B$44:$L$57,2,FALSE()),0)) | W15: =IF(A15="","",W14+(COUNTIF($G$7:G7,"Commercial Junior")+COUNTIF($G$7:G7,"Commercial Senior")+COUNTIF($G$7:G7,"Directrice Commerciale"))*2+IF($B$2="Azura Commerce",1,0)+IFERROR(VLOOKUP(I15,Données!$B$44:$L$57,5,FALSE()),0)+SUMPRODUCT(IFERROR(VLOOKUP($H$7:H15,Données!$B$2:$V$38,22,FALSE()),0))) | X15: =IF(A15="","",X14+COUNTIF($G$7:G7,"Commercial Junior")*1+COUNTIF($G$7:G7,"Commercial Senior")*2+COUNTIF($G$7:G7,"Directrice Commerciale")*3+SUMPRODUCT(IFERROR(VLOOKUP($H$7:H15,Données!$B$2:$V$38,12,FALSE()),0))) | Y15: =IF(A15="","",Y14+IF(MOD(A15-1,4)=0,MAX(1,ROUND(P14*0.05,0)),0)+SUMPRODUCT(IFERROR(VLOOKUP($H$7:H15,Données!$B$2:$V$38,11,FALSE()),0))) | Z15: =IF(A15="","",MAX(0,Z14+MIN(J14+IFERROR(VLOOKUP(H15,Données!$B$2:$V$38,3,FALSE()),0),2+IF(IFERROR(VLOOKUP(H15,Données!$B$2:$V$38,3,FALSE()),0)>0,1,0))+SUMPRODUCT(IFERROR(VLOOKUP($H$7:H15,Données!$B$2:$V$38,21,FALSE()),0)))) | AA15: =IF(A15="","",AA14+IFERROR(VLOOKUP(I15,Données!$B$39:$L$52,8,FALSE()),0)+SUMPRODUCT(IFERROR(VLOOKUP($H$7:H15,Données!$B$2:$R$33,13,FALSE()),0))) | AB15: =IF(A15="","",AB14+IFERROR(VLOOKUP(I15,Données!$B$39:$L$52,6,FALSE()),0)+IFERROR(VLOOKUP(I15,Données!$B$39:$L$52,7,FALSE()),0)) | AC15: =IF(A15="","",V15-W15-X15-Y15-Z15+AA15-AB15) | AD15: =IF(A15="","",T15*3+J15*2+MAX(0,L15)+Q15-MAX(0,-L15)) | AE15: =IF(A15="","",L15-L14) | AF15: =IF(A15="","",T15-T14) | AG15: =IF(A15="","",V15-V14) | AH15: =IF(A15="","",W15+X15+Y15+Z15-W14-X14-Y14-Z14)
A16: =IF(A6+10<=$E$2,10,"") | B16: =IF(A16="","",QUOTIENT(A16-1,4)+1) | C16: =IF(A16="","",MOD(A16-1,4)+1) | J16: =IF(A16="","",MAX(0,J15+IFERROR(VLOOKUP(H16,Données!$B$2:$R$33,3,FALSE()),0)-(2+IF(IFERROR(VLOOKUP(H16,Données!$B$2:$R$33,3,FALSE()),0)>0,1,0)))) | K16: =IF(A16="","",MAX(0,K15+E16+IF($B$2="Manufacture Belvaux",1,0)+IFERROR(VLOOKUP(I16,Données!$B$44:$L$57,4,FALSE()),0)-(COUNTIF($G$7:G7,"Commercial Junior")+COUNTIF($G$7:G7,"Commercial Senior")+COUNTIF($G$7:G7,"Directrice Commerciale"))*2-IF($B$2="Azura Commerce",1,0)+IFERROR(VLOOKUP(H16,Données!$B$2:$V$38,19,FALSE()),0)+SUMPRODUCT(IFERROR(VLOOKUP($H$7:H16,Données!$B$2:$V$38,20,FALSE()),0)))) | L16: =IF(A16="","",L15+D16-IF(F16="Comptant",E16,0)+COUNTIF($G$7:G16,"Commercial Junior")*4+IF($B$2="Véloce Transports",COUNTIF($G$7:G16,"Commercial Senior")*6,0)+IF($B$2="Azura Commerce",2,0)+M15+IFERROR(VLOOKUP(H16,Données!$B$2:$R$33,4,FALSE()),0)+SUMPRODUCT(IFERROR(VLOOKUP($H$7:H16,Données!$B$2:$R$33,10,FALSE()),0))+IFERROR(VLOOKUP(I16,Données!$B$39:$L$52,3,FALSE()),0)-(COUNTIF($G$7:G16,"Commercial Junior")*1+COUNTIF($G$7:G16,"Commercial Senior")*2+COUNTIF($G$7:G16,"Directrice Commerciale")*3)-IF(MOD(A16-1,4)=0,MAX(1,ROUND(P15*0.05,0)),0)+IF($B$2="Synergia Lab",1,0)) | M16: =IF(A16="","",N15+IF($B$2<>"Véloce Transports",COUNTIF($G$7:G16,"Commercial Senior")*6,0)) | N16: =IF(A16="","",COUNTIF($G$7:G16,"Directrice Commerciale")*8+IFERROR(VLOOKUP(I16,Données!$B$39:$L$52,10,FALSE()),0)) | O16: =IF(A16="","",O15+IF(F16="Crédit",E16,0)) | P16: =IF(A16="","",P15+D16+IFERROR(VLOOKUP(H16,Données!$B$2:$R$33,5,FALSE()),0)) | Q16: =IF(A16="","",Q15+IFERROR(VLOOKUP(H16,Données!$B$2:$R$33,6,FALSE()),0)) | R16: =IF(A16="","",J16+K16+MAX(0,L16)+M16+N16) | S16: =IF(A16="","",Q16+P16+O16+MAX(0,-L16)+T16) | T16: =IF(A16="","",R16-Q16-P16-O16-MAX(0,-L16)) | U16: =IF(A16="","",IF(ABS(R16-S16)<0.01,"✓","⚠")) | V16: =IF(A16="","",V15+COUNTIF($G$7:G7,"Commercial Junior")*4+COUNTIF($G$7:G7,"Commercial Senior")*6+COUNTIF($G$7:G7,"Directrice Commerciale")*8+IF($B$2="Azura Commerce",2,0)+IFERROR(VLOOKUP(I16,Données!$B$44:$L$57,2,FALSE()),0)) | W16: =IF(A16="","",W15+(COUNTIF($G$7:G7,"Commercial Junior")+COUNTIF($G$7:G7,"Commercial Senior")+COUNTIF($G$7:G7,"Directrice Commerciale"))*2+IF($B$2="Azura Commerce",1,0)+IFERROR(VLOOKUP(I16,Données!$B$44:$L$57,5,FALSE()),0)+SUMPRODUCT(IFERROR(VLOOKUP($H$7:H16,Données!$B$2:$V$38,22,FALSE()),0))) | X16: =IF(A16="","",X15+COUNTIF($G$7:G7,"Commercial Junior")*1+COUNTIF($G$7:G7,"Commercial Senior")*2+COUNTIF($G$7:G7,"Directrice Commerciale")*3+SUMPRODUCT(IFERROR(VLOOKUP($H$7:H16,Données!$B$2:$V$38,12,FALSE()),0))) | Y16: =IF(A16="","",Y15+IF(MOD(A16-1,4)=0,MAX(1,ROUND(P15*0.05,0)),0)+SUMPRODUCT(IFERROR(VLOOKUP($H$7:H16,Données!$B$2:$V$38,11,FALSE()),0))) | Z16: =IF(A16="","",MAX(0,Z15+MIN(J15+IFERROR(VLOOKUP(H16,Données!$B$2:$V$38,3,FALSE()),0),2+IF(IFERROR(VLOOKUP(H16,Données!$B$2:$V$38,3,FALSE()),0)>0,1,0))+SUMPRODUCT(IFERROR(VLOOKUP($H$7:H16,Données!$B$2:$V$38,21,FALSE()),0)))) | AA16: =IF(A16="","",AA15+IFERROR(VLOOKUP(I16,Données!$B$39:$L$52,8,FALSE()),0)+SUMPRODUCT(IFERROR(VLOOKUP($H$7:H16,Données!$B$2:$R$33,13,FALSE()),0))) | AB16: =IF(A16="","",AB15+IFERROR(VLOOKUP(I16,Données!$B$39:$L$52,6,FALSE()),0)+IFERROR(VLOOKUP(I16,Données!$B$39:$L$52,7,FALSE()),0)) | AC16: =IF(A16="","",V16-W16-X16-Y16-Z16+AA16-AB16) | AD16: =IF(A16="","",T16*3+J16*2+MAX(0,L16)+Q16-MAX(0,-L16)) | AE16: =IF(A16="","",L16-L15) | AF16: =IF(A16="","",T16-T15) | AG16: =IF(A16="","",V16-V15) | AH16: =IF(A16="","",W16+X16+Y16+Z16-W15-X15-Y15-Z15)
A17: =IF(A6+11<=$E$2,11,"") | B17: =IF(A17="","",QUOTIENT(A17-1,4)+1) | C17: =IF(A17="","",MOD(A17-1,4)+1) | J17: =IF(A17="","",MAX(0,J16+IFERROR(VLOOKUP(H17,Données!$B$2:$R$33,3,FALSE()),0)-(2+IF(IFERROR(VLOOKUP(H17,Données!$B$2:$R$33,3,FALSE()),0)>0,1,0)))) | K17: =IF(A17="","",MAX(0,K16+E17+IF($B$2="Manufacture Belvaux",1,0)+IFERROR(VLOOKUP(I17,Données!$B$44:$L$57,4,FALSE()),0)-(COUNTIF($G$7:G7,"Commercial Junior")+COUNTIF($G$7:G7,"Commercial Senior")+COUNTIF($G$7:G7,"Directrice Commerciale"))*2-IF($B$2="Azura Commerce",1,0)+IFERROR(VLOOKUP(H17,Données!$B$2:$V$38,19,FALSE()),0)+SUMPRODUCT(IFERROR(VLOOKUP($H$7:H17,Données!$B$2:$V$38,20,FALSE()),0)))) | L17: =IF(A17="","",L16+D17-IF(F17="Comptant",E17,0)+COUNTIF($G$7:G17,"Commercial Junior")*4+IF($B$2="Véloce Transports",COUNTIF($G$7:G17,"Commercial Senior")*6,0)+IF($B$2="Azura Commerce",2,0)+M16+IFERROR(VLOOKUP(H17,Données!$B$2:$R$33,4,FALSE()),0)+SUMPRODUCT(IFERROR(VLOOKUP($H$7:H17,Données!$B$2:$R$33,10,FALSE()),0))+IFERROR(VLOOKUP(I17,Données!$B$39:$L$52,3,FALSE()),0)-(COUNTIF($G$7:G17,"Commercial Junior")*1+COUNTIF($G$7:G17,"Commercial Senior")*2+COUNTIF($G$7:G17,"Directrice Commerciale")*3)-IF(MOD(A17-1,4)=0,MAX(1,ROUND(P16*0.05,0)),0)+IF($B$2="Synergia Lab",1,0)) | M17: =IF(A17="","",N16+IF($B$2<>"Véloce Transports",COUNTIF($G$7:G17,"Commercial Senior")*6,0)) | N17: =IF(A17="","",COUNTIF($G$7:G17,"Directrice Commerciale")*8+IFERROR(VLOOKUP(I17,Données!$B$39:$L$52,10,FALSE()),0)) | O17: =IF(A17="","",O16+IF(F17="Crédit",E17,0)) | P17: =IF(A17="","",P16+D17+IFERROR(VLOOKUP(H17,Données!$B$2:$R$33,5,FALSE()),0)) | Q17: =IF(A17="","",Q16+IFERROR(VLOOKUP(H17,Données!$B$2:$R$33,6,FALSE()),0)) | R17: =IF(A17="","",J17+K17+MAX(0,L17)+M17+N17) | S17: =IF(A17="","",Q17+P17+O17+MAX(0,-L17)+T17) | T17: =IF(A17="","",R17-Q17-P17-O17-MAX(0,-L17)) | U17: =IF(A17="","",IF(ABS(R17-S17)<0.01,"✓","⚠")) | V17: =IF(A17="","",V16+COUNTIF($G$7:G7,"Commercial Junior")*4+COUNTIF($G$7:G7,"Commercial Senior")*6+COUNTIF($G$7:G7,"Directrice Commerciale")*8+IF($B$2="Azura Commerce",2,0)+IFERROR(VLOOKUP(I17,Données!$B$44:$L$57,2,FALSE()),0)) | W17: =IF(A17="","",W16+(COUNTIF($G$7:G7,"Commercial Junior")+COUNTIF($G$7:G7,"Commercial Senior")+COUNTIF($G$7:G7,"Directrice Commerciale"))*2+IF($B$2="Azura Commerce",1,0)+IFERROR(VLOOKUP(I17,Données!$B$44:$L$57,5,FALSE()),0)+SUMPRODUCT(IFERROR(VLOOKUP($H$7:H17,Données!$B$2:$V$38,22,FALSE()),0))) | X17: =IF(A17="","",X16+COUNTIF($G$7:G7,"Commercial Junior")*1+COUNTIF($G$7:G7,"Commercial Senior")*2+COUNTIF($G$7:G7,"Directrice Commerciale")*3+SUMPRODUCT(IFERROR(VLOOKUP($H$7:H17,Données!$B$2:$V$38,12,FALSE()),0))) | Y17: =IF(A17="","",Y16+IF(MOD(A17-1,4)=0,MAX(1,ROUND(P16*0.05,0)),0)+SUMPRODUCT(IFERROR(VLOOKUP($H$7:H17,Données!$B$2:$V$38,11,FALSE()),0))) | Z17: =IF(A17="","",MAX(0,Z16+MIN(J16+IFERROR(VLOOKUP(H17,Données!$B$2:$V$38,3,FALSE()),0),2+IF(IFERROR(VLOOKUP(H17,Données!$B$2:$V$38,3,FALSE()),0)>0,1,0))+SUMPRODUCT(IFERROR(VLOOKUP($H$7:H17,Données!$B$2:$V$38,21,FALSE()),0)))) | AA17: =IF(A17="","",AA16+IFERROR(VLOOKUP(I17,Données!$B$39:$L$52,8,FALSE()),0)+SUMPRODUCT(IFERROR(VLOOKUP($H$7:H17,Données!$B$2:$R$33,13,FALSE()),0))) | AB17: =IF(A17="","",AB16+IFERROR(VLOOKUP(I17,Données!$B$39:$L$52,6,FALSE()),0)+IFERROR(VLOOKUP(I17,Données!$B$39:$L$52,7,FALSE()),0)) | AC17: =IF(A17="","",V17-W17-X17-Y17-Z17+AA17-AB17) | AD17: =IF(A17="","",T17*3+J17*2+MAX(0,L17)+Q17-MAX(0,-L17)) | AE17: =IF(A17="","",L17-L16) | AF17: =IF(A17="","",T17-T16) | AG17: =IF(A17="","",V17-V16) | AH17: =IF(A17="","",W17+X17+Y17+Z17-W16-X16-Y16-Z16)
A18: =IF(A6+12<=$E$2,12,"") | B18: =IF(A18="","",QUOTIENT(A18-1,4)+1) | C18: =IF(A18="","",MOD(A18-1,4)+1) | J18: =IF(A18="","",MAX(0,J17+IFERROR(VLOOKUP(H18,Données!$B$2:$R$33,3,FALSE()),0)-(2+IF(IFERROR(VLOOKUP(H18,Données!$B$2:$R$33,3,FALSE()),0)>0,1,0)))) | K18: =IF(A18="","",MAX(0,K17+E18+IF($B$2="Manufacture Belvaux",1,0)+IFERROR(VLOOKUP(I18,Données!$B$44:$L$57,4,FALSE()),0)-(COUNTIF($G$7:G7,"Commercial Junior")+COUNTIF($G$7:G7,"Commercial Senior")+COUNTIF($G$7:G7,"Directrice Commerciale"))*2-IF($B$2="Azura Commerce",1,0)+IFERROR(VLOOKUP(H18,Données!$B$2:$V$38,19,FALSE()),0)+SUMPRODUCT(IFERROR(VLOOKUP($H$7:H18,Données!$B$2:$V$38,20,FALSE()),0)))) | L18: =IF(A18="","",L17+D18-IF(F18="Comptant",E18,0)+COUNTIF($G$7:G18,"Commercial Junior")*4+IF($B$2="Véloce Transports",COUNTIF($G$7:G18,"Commercial Senior")*6,0)+IF($B$2="Azura Commerce",2,0)+M17+IFERROR(VLOOKUP(H18,Données!$B$2:$R$33,4,FALSE()),0)+SUMPRODUCT(IFERROR(VLOOKUP($H$7:H18,Données!$B$2:$R$33,10,FALSE()),0))+IFERROR(VLOOKUP(I18,Données!$B$39:$L$52,3,FALSE()),0)-(COUNTIF($G$7:G18,"Commercial Junior")*1+COUNTIF($G$7:G18,"Commercial Senior")*2+COUNTIF($G$7:G18,"Directrice Commerciale")*3)-IF(MOD(A18-1,4)=0,MAX(1,ROUND(P17*0.05,0)),0)+IF($B$2="Synergia Lab",1,0)) | M18: =IF(A18="","",N17+IF($B$2<>"Véloce Transports",COUNTIF($G$7:G18,"Commercial Senior")*6,0)) | N18: =IF(A18="","",COUNTIF($G$7:G18,"Directrice Commerciale")*8+IFERROR(VLOOKUP(I18,Données!$B$39:$L$52,10,FALSE()),0)) | O18: =IF(A18="","",O17+IF(F18="Crédit",E18,0)) | P18: =IF(A18="","",P17+D18+IFERROR(VLOOKUP(H18,Données!$B$2:$R$33,5,FALSE()),0)) | Q18: =IF(A18="","",Q17+IFERROR(VLOOKUP(H18,Données!$B$2:$R$33,6,FALSE()),0)) | R18: =IF(A18="","",J18+K18+MAX(0,L18)+M18+N18) | S18: =IF(A18="","",Q18+P18+O18+MAX(0,-L18)+T18) | T18: =IF(A18="","",R18-Q18-P18-O18-MAX(0,-L18)) | U18: =IF(A18="","",IF(ABS(R18-S18)<0.01,"✓","⚠")) | V18: =IF(A18="","",V17+COUNTIF($G$7:G7,"Commercial Junior")*4+COUNTIF($G$7:G7,"Commercial Senior")*6+COUNTIF($G$7:G7,"Directrice Commerciale")*8+IF($B$2="Azura Commerce",2,0)+IFERROR(VLOOKUP(I18,Données!$B$44:$L$57,2,FALSE()),0)) | W18: =IF(A18="","",W17+(COUNTIF($G$7:G7,"Commercial Junior")+COUNTIF($G$7:G7,"Commercial Senior")+COUNTIF($G$7:G7,"Directrice Commerciale"))*2+IF($B$2="Azura Commerce",1,0)+IFERROR(VLOOKUP(I18,Données!$B$44:$L$57,5,FALSE()),0)+SUMPRODUCT(IFERROR(VLOOKUP($H$7:H18,Données!$B$2:$V$38,22,FALSE()),0))) | X18: =IF(A18="","",X17+COUNTIF($G$7:G7,"Commercial Junior")*1+COUNTIF($G$7:G7,"Commercial Senior")*2+COUNTIF($G$7:G7,"Directrice Commerciale")*3+SUMPRODUCT(IFERROR(VLOOKUP($H$7:H18,Données!$B$2:$V$38,12,FALSE()),0))) | Y18: =IF(A18="","",Y17+IF(MOD(A18-1,4)=0,MAX(1,ROUND(P17*0.05,0)),0)+SUMPRODUCT(IFERROR(VLOOKUP($H$7:H18,Données!$B$2:$V$38,11,FALSE()),0))) | Z18: =IF(A18="","",MAX(0,Z17+MIN(J17+IFERROR(VLOOKUP(H18,Données!$B$2:$V$38,3,FALSE()),0),2+IF(IFERROR(VLOOKUP(H18,Données!$B$2:$V$38,3,FALSE()),0)>0,1,0))+SUMPRODUCT(IFERROR(VLOOKUP($H$7:H18,Données!$B$2:$V$38,21,FALSE()),0)))) | AA18: =IF(A18="","",AA17+IFERROR(VLOOKUP(I18,Données!$B$39:$L$52,8,FALSE()),0)+SUMPRODUCT(IFERROR(VLOOKUP($H$7:H18,Données!$B$2:$R$33,13,FALSE()),0))) | AB18: =IF(A18="","",AB17+IFERROR(VLOOKUP(I18,Données!$B$39:$L$52,6,FALSE()),0)+IFERROR(VLOOKUP(I18,Données!$B$39:$L$52,7,FALSE()),0)) | AC18: =IF(A18="","",V18-W18-X18-Y18-Z18+AA18-AB18) | AD18: =IF(A18="","",T18*3+J18*2+MAX(0,L18)+Q18-MAX(0,-L18)) | AE18: =IF(A18="","",L18-L17) | AF18: =IF(A18="","",T18-T17) | AG18: =IF(A18="","",V18-V17) | AH18: =IF(A18="","",W18+X18+Y18+Z18-W17-X17-Y17-Z17)
