Workbook

Sheet Simulation
A1: SIMULATION JEU INTERACTIF
A3: Entreprise : | D3: Manufacture Belvaux
A4: Nombre de trimestres : | D4: 6
A5: Trimestre initial : | D5: 1
A11: TRIMESTRE | B11: AVANT | C11: DÉCISIONS | D11: MONTANT | E11: APRÈS | F11: NOTE
A12: TRIMESTRE 1
A13: 📋 DÉCISIONS
A15: Emprunt demandé : | D15: 0
A16: Achat de stock : | D16: 0
A17: Mode de trésorerie : | D17: Tréso
A18: Recrutement : | D18: Aucun
A19: Carte action : | D19: Aucune
A20: Événement : | D20: Aucun
A22: ⚙️ EFFETS AUTOMATIQUES
A23: Charges courantes | D23: -2000
A24: Amortissements | D24: =MAX(-VLOOKUP($D$3,Données!$A$65:$J$68,6,0)*1000,-C52)
A25: Remboursements | D25: =IF(C60>0,-1000,0)
A26: Agios | D26: =IF(C62>0,MAX(1000,ROUNDUP(C62*0.10/1000,0)*1000),0)
A27: Règlement dettes | D27: 0
A30: Stock acheté | D30: =$D$16
A31: Stock à payer | D31: =IF($D$17="Tréso",-$D$16,0)
A34: Capacité prod. | D34: =4+IFERROR(VLOOKUP($D$19,Données!$A$2:$V$38,18,0),0)
A35: Stocks dispo | D35: =C53+D30
A36: Unités vendues | D36: 0
A37: CA (Chiffre affaires) | D37: =D36*2000
A38: CMV (Coût matière) | D38: =-D36*1000
A41: Immobilisations | D41: =IFERROR(VLOOKUP($D$19,Données!$A$2:$V$38,4,0),0)
A42: Trésorerie | D42: =IFERROR(VLOOKUP($D$19,Données!$A$2:$V$38,5,0),0)
A43: Stocks | D43: =IFERROR(VLOOKUP($D$19,Données!$A$2:$V$38,19,0),0)
A46: Trésorerie | D46: =IFERROR(VLOOKUP($D$18,Données!$A$2:$V$38,5,0),0)
A47: Stocks | D47: 0
A51: 📊 BILAN
A52: Immobilisations | C52: =VLOOKUP($D$3,Données!$A$65:$J$68,5,0) | E52: =MAX(0,C52+D24+D41)
A53: Stocks | C53: =VLOOKUP($D$3,Données!$A$65:$J$68,7,0) | E53: =C53+D30+D43+D47
A54: Créances clients | C54: 0 | E54: =C54+D37
A55: Trésorerie | C55: =VLOOKUP($D$3,Données!$A$65:$J$68,8,0) | E55: =C55+D23+D25+D31+D42+D46
A56: TOTAL ACTIF | C56: =SUM(C52:C55) | E56: =SUM(E52:E55)
A59: Capitaux propres | C59: =VLOOKUP($D$3,Données!$A$65:$J$68,9,0) | E59: =C59
A60: Emprunts | C60: =VLOOKUP($D$3,Données!$A$65:$J$68,10,0) | E60: =C60+$D$15+D25
A61: Dettes fournisseurs | C61: 0 | E61: =C61
A62: Découvert | C62: 0 | E62: =C62+D26
A63: Résultat | C63: 0 | E63: =E56-(E59+E60+E61+E62)
A64: TOTAL PASSIF | C64: =SUM(C59:C63) | E64: =SUM(E59:E63)
A65: Équilibre (APRÈS) | C65: =E56-E64
A66: 📈 COMPTE DE RÉSULTAT — TRIMESTRE 1
A67: POSTE | B67: ± | D67: MONTANT | F67: NOTE
A68: CA ventes | B68: (+) | D68: =D37 | F68: Unités × 2 000 €/u
A69: Produits except. | B69: (+) | D69: =IFERROR(VLOOKUP($D$19,Données!$A$2:$V$38,14,0),0)+IFERROR(VLOOKUP($D$20,Données!$B$45:$L$57,8,0),0)+IFERROR(VLOOKUP($D$19,Données!$A$2:$V$38,15,0),0)+IFERROR(VLOOKUP($D$20,Données!$B$45:$L$57,9,0),0) | F69: Subvention, remb. assurance
A70: TOTAL PRODUITS | B70: Σ | D70: =D68+D69
A71: CMV | B71: (−) | D71: =D38 | F71: Stocks à valeur d'achat
A72: Ch. personnel | B72: (−) | D72: =IFERROR(VLOOKUP($D$18,Données!$A$2:$V$38,9,0),0)+IFERROR(VLOOKUP($D$19,Données!$A$2:$V$38,9,0),0) | F72: Salaires commerciaux
A73: Ch. fixes & serv. | B73: (−) | D73: =-2000+IFERROR(VLOOKUP($D$19,Données!$A$2:$V$38,10,0),0)+IFERROR(VLOOKUP($D$20,Données!$B$45:$L$57,3,0),0) | F73: Loyer -2000 + cartes
A74: Dotations amort. | B74: (−) | D74: =D24 | F74: Amortissements
A75: Ch. intérêt | B75: (−) | D75: =-D26+IFERROR(VLOOKUP($D$19,Données!$A$2:$V$38,12,0),0) | F75: Agios + intérêts emprunt
A76: TOTAL CHARGES | B76: Σ | D76: =SUM(D71:D75)
A77: RÉSULTAT NET | B77: = | D77: =D70+D76
A79: TRIMESTRE 2
A80: 📋 DÉCISIONS
A82: Emprunt demandé : | D82: 0
A83: Achat de stock : | D83: 0
A84: Mode de trésorerie : | D84: Tréso
A85: Recrutement : | D85: Aucun
A86: Carte action : | D86: Aucune
A87: Événement : | D87: Aucun
A89: ⚙️ EFFETS AUTOMATIQUES
A90: Charges courantes | D90: -2000
A91: Amortissements | D91: =MAX(-VLOOKUP($D$3,Données!$A$65:$J$68,6,0)*1000,-C119)
A92: Remboursements | D92: =IF(C127>0,-1000,0)
A93: Agios | D93: =IF(C129>0,MAX(1000,ROUNDUP(C129*0.10/1000,0)*1000),0)
A94: Règlement dettes | D94: 0
A97: Stock acheté | D97: =$D$83
A98: Stock à payer | D98: =IF($D$84="Tréso",-$D$83,0)
A101: Capacité prod. | D101: =4+IFERROR(VLOOKUP($D$86,Données!$A$2:$V$38,18,0),0)
A102: Stocks dispo | D102: =C120+D97
A103: Unités vendues | D103: 0
A104: CA (Chiffre affaires) | D104: =D103*2000
A105: CMV (Coût matière) | D105: =-D103*1000
A108: Immobilisations | D108: =IFERROR(VLOOKUP($D$86,Données!$A$2:$V$38,4,0),0)
A109: Trésorerie | D109: =IFERROR(VLOOKUP($D$86,Données!$A$2:$V$38,5,0),0)
A110: Stocks | D110: =IFERROR(VLOOKUP($D$86,Données!$A$2:$V$38,19,0),0)
A113: Trésorerie | D113: =IFERROR(VLOOKUP($D$85,Données!$A$2:$V$38,5,0),0)
A114: Stocks | D114: 0
A118: 📊 BILAN
A119: Immobilisations | C119: =E52 | E119: =MAX(0,C119+D91+D108)
A120: Stocks | C120: =E53 | E120: =C120+D97+D110+D114
A121: Créances clients | C121: =E54 | E121: =C121+D104
A122: Trésorerie | C122: =E55 | E122: =C122+D90+D92+D98+D109+D113
A123: TOTAL ACTIF | C123: =SUM(C119:C122) | E123: =SUM(E119:E122)
A126: Capitaux propres | C126: =E59 | E126: =C126
A127: Emprunts | C127: =E60 | E127: =C127+$D$82+D92
A128: Dettes fournisseurs | C128: =E61 | E128: =C128
A129: Découvert | C129: =E62 | E129: =C129+D93
A130: Résultat | C130: =E63 | E130: =E123-(E126+E127+E128+E129)
A131: TOTAL PASSIF | C131: =SUM(C126:C130) | E131: =SUM(E126:E130)
A132: Équilibre (APRÈS) | C132: =E123-E131
A133: 📈 COMPTE DE RÉSULTAT — TRIMESTRE 2
A134: POSTE | B134: ± | D134: MONTANT | F134: NOTE
A135: CA ventes | B135: (+) | D135: =D104 | F135: Unités × 2 000 €/u
A136: Produits except. | B136: (+) | D136: =IFERROR(VLOOKUP($D$86,Données!$A$2:$V$38,14,0),0)+IFERROR(VLOOKUP($D$87,Données!$B$45:$L$57,8,0),0)+IFERROR(VLOOKUP($D$86,Données!$A$2:$V$38,15,0),0)+IFERROR(VLOOKUP($D$87,Données!$B$45:$L$57,9,0),0) | F136: Subvention, remb. assurance
A137: TOTAL PRODUITS | B137: Σ | D137: =D135+D136
...

Sheet Données
A1: ID | B1: Titre | C1: Catégorie | D1: imm_immo | E1: imm_treso | F1: imm_emprunts | G1: imm_capitaux | H1: imm_servExt | I1: imm_charPers | J1: rec_servExt | K1: rec_treso | L1: rec_charInt | M1: rec_charPers | N1: rec_revExcep | O1: rec_prodFin | P1: clientType | Q1: nbClients | R1: capaciteBonus | S1: imm_stocks | T1: rec_stocks | U1: rec_amort | V1: rec_cmv
A2: Commercial Junior | B2: Commercial Junior | C2: Commercial | D2: 0 | E2: -1000 | F2: 0 | G2: 0 | H2: 0 | I2: 1000 | J2: 0 | K2: -1000 | L2: 0 | M2: 1000 | N2: 0 | O2: 0 | P2: 0 | Q2: 0 | R2: 0 | S2: 0 | T2: 0 | U2: 0 | V2: 0
A3: Commercial Senior | B3: Commercial Senior | C3: Commercial | D3: 0 | E3: -2000 | F3: 0 | G3: 0 | H3: 0 | I3: 2000 | J3: 0 | K3: -2000 | L3: 0 | M3: 2000 | N3: 0 | O3: 0 | P3: 0 | Q3: 0 | R3: 0 | S3: 0 | T3: 0 | U3: 0 | V3: 0
A4: Directrice Commerciale | B4: Directrice Commerciale | C4: Commercial | D4: 0 | E4: -3000 | F4: 0 | G4: 0 | H4: 0 | I4: 3000 | J4: 0 | K4: -3000 | L4: 0 | M4: 3000 | N4: 0 | O4: 0 | P4: 0 | Q4: 0 | R4: 0 | S4: 0 | T4: 0 | U4: 0 | V4: 0
A5: Camionnette | B5: Camionnette | C5: Transport | D5: 8000 | E5: -8000 | F5: 0 | G5: 0 | H5: 0 | I5: 0 | J5: 1000 | K5: -1000 | L5: 0 | M5: 0 | N5: 0 | O5: 0 | P5: 1 | Q5: 1 | R5: 6 | S5: 0 | T5: 0 | U5: 0 | V5: 0
A6: Berline | B6: Berline | C6: Transport | D6: 8000 | E6: -8000 | F6: 0 | G6: 0 | H6: 0 | I6: 0 | J6: 2000 | K6: -2000 | L6: 0 | M6: 0 | N6: 0 | O6: 0 | P6: 0 | Q6: 0 | R6: 0 | S6: 0 | T6: 0 | U6: 0 | V6: 0
A7: Site Internet | B7: Site Internet | C7: Digital | D7: 4000 | E7: -4000 | F7: 0 | G7: 0 | H7: 0 | I7: 0 | J7: 1000 | K7: -1000 | L7: 0 | M7: 0 | N7: 0 | O7: 0 | P7: 1 | Q7: 1 | R7: 0 | S7: 0 | T7: 0 | U7: 0 | V7: 0
A8: RSE | B8: RSE | C8: Compliance | D8: 2000 | E8: 0 | F8: 2000 | G8: 0 | H8: 0 | I8: 0 | J8: 1000 | K8: -1000 | L8: 0 | M8: 0 | N8: 0 | O8: 0 | P8: 1 | Q8: 1 | R8: 0 | S8: 0 | T8: 0 | U8: 0 | V8: 0
A9: R&D | B9: R&D | C9: Innovation | D9: 5000 | E9: -5000 | F9: 0 | G9: 0 | H9: 0 | I9: 0 | J9: 2000 | K9: 0 | L9: 0 | M9: 0 | N9: 1000 | O9: 0 | P9: 2 | Q9: 1 | R9: 0 | S9: 0 | T9: 0 | U9: 0 | V9: 0
A10: Expansion | B10: Expansion | C10: Growth | D10: 8000 | E10: -8000 | F10: 0 | G10: 0 | H10: 0 | I10: 0 | J10: 1000 | K10: -1000 | L10: 0 | M10: 0 | N10: 0 | O10: 0 | P10: 3 | Q10: 1 | R10: 10 | S10: 0 | T10: 0 | U10: 0 | V10: 0
A11: Certification ISO | B11: Certification ISO | C11: Compliance | D11: 5000 | E11: -5000 | F11: 0 | G11: 0 | H11: 0 | I11: 0 | J11: 1000 | K11: -1000 | L11: 0 | M11: 0 | N11: 0 | O11: 0 | P11: 3 | Q11: 1 | R11: 0 | S11: 0 | T11: 0 | U11: 0 | V11: 0
A12: Application Mobile | B12: Application Mobile | C12: Digital | D12: 4000 | E12: -4000 | F12: 0 | G12: 0 | H12: 0 | I12: 0 | J12: 1000 | K12: -1000 | L12: 0 | M12: 0 | N12: 0 | O12: 0 | P12: 1 | Q12: 2 | R12: 0 | S12: 0 | T12: 0 | U12: 0 | V12: 0
A13: Prêt Bancaire | B13: Prêt Bancaire | C13: Finance | D13: 0 | E13: 5000 | F13: 5000 | G13: 0 | H13: 0 | I13: 0 | J13: 0 | K13: -1000 | L13: 1000 | M13: 0 | N13: 0 | O13: 0 | P13: 0 | Q13: 0 | R13: 0 | S13: 0 | T13: 0 | U13: 0 | V13: 0
... A38: Sous-traitance | B38: Sous-traitance | C38: Tactique | D38: 0 | E38: 0 | F38: 0 | G38: 0 | H38: 0 | I38: 0 | J38: 2000 | K38: -4000 | L38: 0 | M38: 0 | N38: 0 | O38: 0 | P38: 0 | Q38: 0 | R38: 0 | S38: 0 | T38: 2000 | U38: 0 | V38: 0
A44: ID | B44: Titre | C44: ventes | D44: treso | E44: stocks | F44: achats | G44: chargesExcep | H44: impots | I44: revenusExcep | J44: prodFin | K44: creancesPlus2 | L44: annulable
B45: Client VIP | C45: 2000 | D45: 2000 | E45: -2000 | F45: 2000 | G45: 0 | H45: 0 | I45: 0 | J45: 0 | K45: 0 | L45: 0
B46: Contrôle Fiscal | C46: 0 | D46: -2000 | E46: 0 | F46: 0 | G46: 0 | H46: 2000 | I46: 0 | J46: 0 | K46: 0 | L46: 1
B47: Subvention Innovation | C47: 0 | D47: 3000 | E47: 0 | F47: 0 | G47: 0 | H47: 0 | I47: 3000 | J47: 0 | K47: 0 | L47: 0
B48: Placement Financier | C48: 0 | D48: 1000 | E48: 0 | F48: 0 | G48: 0 | H48: 0 | I48: 0 | J48: 1000 | K48: 0 | L48: 0
B49: Crise Sanitaire | C49: 0 | D49: -2000 | E49: 0 | F49: 0 | G49: 2000 | H49: 0 | I49: 0 | J49: 0 | K49: 0 | L49: 1
B50: Incendie | C50: 0 | D50: 2000 | E50: 0 | F50: 0 | G50: 0 | H50: 0 | I50: 2000 | J50: 0 | K50: 0 | L50: 0
B51: Grève | C51: 0 | D51: -2000 | E51: 0 | F51: 0 | G51: 2000 | H51: 0 | I51: 0 | J51: 0 | K51: 0 | L51: 1
B52: Bouche à Oreille | C52: 1000 | D52: 1000 | E52: 0 | F52: 0 | G52: 0 | H52: 0 | I52: 0 | J52: 0 | K52: 0 | L52: 0
B53: Perte de Données | C53: 0 | D53: -2000 | E53: 0 | F53: 0 | G53: 2000 | H53: 0 | I53: 0 | J53: 0 | K53: 0 | L53: 1
B54: Développement Durable | C54: 3000 | D54: 0 | E54: -3000 | F54: 3000 | G54: 0 | H54: 0 | I54: 0 | J54: 0 | K54: 3000 | L54: 0
B55: Prix PME | C55: 0 | D55: 2000 | E55: 0 | F55: 0 | G55: 0 | H55: 0 | I55: 2000 | J55: 0 | K55: 0 | L55: 0
B56: Rupture Fournisseur | C56: 0 | D56: -2000 | E56: 0 | F56: 0 | G56: 2000 | H56: 0 | I56: 0 | J56: 0 | K56: 0 | L56: 0
B57: Litige Commercial | C57: 0 | D57: -3000 | E57: 0 | F57: 0 | G57: 3000 | H57: 0 | I57: 0 | J57: 0 | K57: 0 | L57: 1
A64: Nom | B64: Icon | C64: Type | D64: Spécialité | E64: immo_init | F64: nb_immo_items | G64: stocks_init | H64: treso_init | I64: capitaux_init | J64: emprunts_init
A65: Manufacture Belvaux | B65: 🏭 | C65: Production | D65: +1 prodStockée +1 stocks | E65: 16000 | F65: 2 | G65: 4000 | H65: 8000 | I65: 20000 | J65: 8000
A66: Véloce Transports | B66: 🚚 | C66: Logistique | D66: Encaissement -1 délai | E66: 16000 | F66: 2 | G66: 4000 | H66: 8000 | I66: 20000 | J66: 8000
A67: Azura Commerce | B67: 🏪 | C67: Commerce | D67: +1 client Particulier/tour | E67: 16000 | F67: 2 | G67: 4000 | H67: 8000 | I67: 20000 | J67: 8000
A68: Synergia Lab | B68: 💡 | C68: Innovation | D68: +1 prodFinanciers +1 tréso | E68: 13000 | F68: 2 | G68: 4000 | H68: 8000 | I68: 17000 | J68: 8000
